{"match_id": "17e86678-094d-4b90-8b73-87d28aeca271", "map_id": "GrandRift", "date": "2026-02-10", "human_count": 1, "bot_count": 0, "event_counts": {"Position": 68, "Loot": 25, "BotKill": 12}, "events": [{"user_id": "24bd210d-3b53-4f06-acf1-a0e0385641b6", "is_human": true, "event": "Position", "u": 0.3582, "v": 0.1941, "ts": 1770}, {"user_id": "24bd210d-3b53-4f06-acf1-a0e0385641b6", "is_human": true, "event": "Position", "u": 0.3684, "v": 0.229, "ts": 1770}, {"user_id": "24bd210d-3b53-4f06-acf1-a0e0385641b6", "is_human": true, "event": "Position", "u": 0.3929, "v": 0.2341, "ts": 1770}, {"user_id": "24bd210d-3b53-4f06-acf1-a0e0385641b6", "is_human": true, "event": "Position", "u": 0.3794, "v": 0.2637, "ts": 1770}, {"user_id": "24bd210d-3b53-4f06-acf1-a0e0385641b6", "is_human": true, "event": "Position", "u": 0.3746, "v": 0.3089, "ts": 1770}, {"user_id": "24bd210d-3b53-4f06-acf1-a0e0385641b6", "is_human": true, "event": "Position", "u": 0.3347, "v": 0.3249, "ts": 1770}, {"user_id": "24bd210d-3b53-4f06-acf1-a0e0385641b6", "is_human": true, "event": "Position", "u": 0.3046, "v": 0.3542, "ts": 1770}, {"user_id": "24bd210d-3b53-4f06-acf1-a0e0385641b6", "is_human": true, "event": "Position", "u": 0.3015, "v": 0.3768, "ts": 1770}, {"user_id": "24bd210d-3b53-4f06-acf1-a0e0385641b6", "is_human": true, "event": "Position", "u": 0.287, "v": 0.409, "ts": 1770}, {"user_id": "24bd210d-3b53-4f06-acf1-a0e0385641b6", "is_human": true, "event": "Position", "u": 0.2702, "v": 0.4202, "ts": 1770}, {"user_id": "24bd210d-3b53-4f06-acf1-a0e0385641b6", "is_human": true, "event": "Position", "u": 0.2438, "v": 0.4129, "ts": 1770}, {"user_id": "24bd210d-3b53-4f06-acf1-a0e0385641b6", "is_human": true, "event": "Position", "u": 0.2423, "v": 0.4152, "ts": 1770}, {"user_id": "24bd210d-3b53-4f06-acf1-a0e0385641b6", "is_human": true, "event": "Position", "u": 0.2313, "v": 0.4078, "ts": 1770}, {"user_id": "24bd210d-3b53-4f06-acf1-a0e0385641b6", "is_human": true, "event": "Loot", "u": 0.2313, "v": 0.4078, "ts": 1770}, {"user_id": "24bd210d-3b53-4f06-acf1-a0e0385641b6", "is_human": true, "event": "Loot", "u": 0.2313, "v": 0.4078, "ts": 1770}, {"user_id": "24bd210d-3b53-4f06-acf1-a0e0385641b6", "is_human": true, "event": "Position", "u": 0.2253, "v": 0.3991, "ts": 1770}, {"user_id": "24bd210d-3b53-4f06-acf1-a0e0385641b6", "is_human": true, "event": "Loot", "u": 0.2253, "v": 0.3991, "ts": 1770}, {"user_id": "24bd210d-3b53-4f06-acf1-a0e0385641b6", "is_human": true, "event": "Position", "u": 0.2362, "v": 0.4081, "ts": 1770}, {"user_id": "24bd210d-3b53-4f06-acf1-a0e0385641b6", "is_human": true, "event": "Position", "u": 0.2429, "v": 0.4153, "ts": 1770}, {"user_id": "24bd210d-3b53-4f06-acf1-a0e0385641b6", "is_human": true, "event": "Position", "u": 0.2361, "v": 0.4164, "ts": 1770}, {"user_id": "24bd210d-3b53-4f06-acf1-a0e0385641b6", "is_human": true, "event": "Position", "u": 0.2274, "v": 0.4157, "ts": 1770}, {"user_id": "24bd210d-3b53-4f06-acf1-a0e0385641b6", "is_human": true, "event": "Position", "u": 0.2233, "v": 0.4104, "ts": 1770}, {"user_id": "24bd210d-3b53-4f06-acf1-a0e0385641b6", "is_human": true, "event": "Position", "u": 0.2007, "v": 0.4079, "ts": 1770}, {"user_id": "24bd210d-3b53-4f06-acf1-a0e0385641b6", "is_human": true, "event": "Position", "u": 0.2214, "v": 0.4343, "ts": 1770}, {"user_id": "24bd210d-3b53-4f06-acf1-a0e0385641b6", "is_human": true, "event": "Position", "u": 0.2393, "v": 0.4492, "ts": 1770}, {"user_id": "24bd210d-3b53-4f06-acf1-a0e0385641b6", "is_human": true, "event": "Position", "u": 0.2621, "v": 0.4807, "ts": 1770}, {"user_id": "24bd210d-3b53-4f06-acf1-a0e0385641b6", "is_human": true, "event": "Position", "u": 0.289, "v": 0.4963, "ts": 1770}, {"user_id": "24bd210d-3b53-4f06-acf1-a0e0385641b6", "is_human": true, "event": "Position", "u": 0.3334, "v": 0.5044, "ts": 1770}, {"user_id": "24bd210d-3b53-4f06-acf1-a0e0385641b6", "is_human": true, "event": "Position", "u": 0.3557, "v": 0.5221, "ts": 1770}, {"user_id": "24bd210d-3b53-4f06-acf1-a0e0385641b6", "is_human": true, "event": "Position", "u": 0.3684, "v": 0.5254, "ts": 1770}, {"user_id": "24bd210d-3b53-4f06-acf1-a0e0385641b6", "is_human": true, "event": "BotKill", "u": 0.3692, "v": 0.5298, "ts": 1770}, {"user_id": "24bd210d-3b53-4f06-acf1-a0e0385641b6", "is_human": true, "event": "Position", "u": 0.3813, "v": 0.5283, "ts": 1770}, {"user_id": "24bd210d-3b53-4f06-acf1-a0e0385641b6", "is_human": true, "event": "Position", "u": 0.383, "v": 0.5738, "ts": 1770}, {"user_id": "24bd210d-3b53-4f06-acf1-a0e0385641b6", "is_human": true, "event": "Loot", "u": 0.3817, "v": 0.5764, "ts": 1770}, {"user_id": "24bd210d-3b53-4f06-acf1-a0e0385641b6", "is_human": true, "event": "Position", "u": 0.3629, "v": 0.5745, "ts": 1770}, {"user_id": "24bd210d-3b53-4f06-acf1-a0e0385641b6", "is_human": true, "event": "Loot", "u": 0.3607, "v": 0.5802, "ts": 1770}, {"user_id": "24bd210d-3b53-4f06-acf1-a0e0385641b6", "is_human": true, "event": "Loot", "u": 0.3607, "v": 0.5802, "ts": 1770}, {"user_id": "24bd210d-3b53-4f06-acf1-a0e0385641b6", "is_human": true, "event": "Loot", "u": 0.3607, "v": 0.5802, "ts": 1770}, {"user_id": "24bd210d-3b53-4f06-acf1-a0e0385641b6", "is_human": true, "event": "Position", "u": 0.3721, "v": 0.5742, "ts": 1770}, {"user_id": "24bd210d-3b53-4f06-acf1-a0e0385641b6", "is_human": true, "event": "Position", "u": 0.3813, "v": 0.5652, "ts": 1770}, {"user_id": "24bd210d-3b53-4f06-acf1-a0e0385641b6", "is_human": true, "event": "Position", "u": 0.3992, "v": 0.5865, "ts": 1770}, {"user_id": "24bd210d-3b53-4f06-acf1-a0e0385641b6", "is_human": true, "event": "Position", "u": 0.4128, "v": 0.6253, "ts": 1770}, {"user_id": "24bd210d-3b53-4f06-acf1-a0e0385641b6", "is_human": true, "event": "Position", "u": 0.4079, "v": 0.6693, "ts": 1770}, {"user_id": "24bd210d-3b53-4f06-acf1-a0e0385641b6", "is_human": true, "event": "Loot", "u": 0.4086, "v": 0.6739, "ts": 1770}, {"user_id": "24bd210d-3b53-4f06-acf1-a0e0385641b6", "is_human": true, "event": "Loot", "u": 0.4086, "v": 0.6739, "ts": 1770}, {"user_id": "24bd210d-3b53-4f06-acf1-a0e0385641b6", "is_human": true, "event": "Loot", "u": 0.4086, "v": 0.6739, "ts": 1770}, {"user_id": "24bd210d-3b53-4f06-acf1-a0e0385641b6", "is_human": true, "event": "Position", "u": 0.4086, "v": 0.6739, "ts": 1770}, {"user_id": "24bd210d-3b53-4f06-acf1-a0e0385641b6", "is_human": true, "event": "Position", "u": 0.4292, "v": 0.6533, "ts": 1770}, {"user_id": "24bd210d-3b53-4f06-acf1-a0e0385641b6", "is_human": true, "event": "Position", "u": 0.4138, "v": 0.6466, "ts": 1770}, {"user_id": "24bd210d-3b53-4f06-acf1-a0e0385641b6", "is_human": true, "event": "Position", "u": 0.4265, "v": 0.6285, "ts": 1770}, {"user_id": "24bd210d-3b53-4f06-acf1-a0e0385641b6", "is_human": true, "event": "Position", "u": 0.419, "v": 0.6112, "ts": 1770}, {"user_id": "24bd210d-3b53-4f06-acf1-a0e0385641b6", "is_human": true, "event": "BotKill", "u": 0.4145, "v": 0.6122, "ts": 1770}, {"user_id": "24bd210d-3b53-4f06-acf1-a0e0385641b6", "is_human": true, "event": "Position", "u": 0.4206, "v": 0.6103, "ts": 1770}, {"user_id": "24bd210d-3b53-4f06-acf1-a0e0385641b6", "is_human": true, "event": "Position", "u": 0.428, "v": 0.6152, "ts": 1770}, {"user_id": "24bd210d-3b53-4f06-acf1-a0e0385641b6", "is_human": true, "event": "Loot", "u": 0.4307, "v": 0.616, "ts": 1770}, {"user_id": "24bd210d-3b53-4f06-acf1-a0e0385641b6", "is_human": true, "event": "Loot", "u": 0.4307, "v": 0.616, "ts": 1770}, {"user_id": "24bd210d-3b53-4f06-acf1-a0e0385641b6", "is_human": true, "event": "Loot", "u": 0.4307, "v": 0.616, "ts": 1770}, {"user_id": "24bd210d-3b53-4f06-acf1-a0e0385641b6", "is_human": true, "event": "Loot", "u": 0.4307, "v": 0.616, "ts": 1770}, {"user_id": "24bd210d-3b53-4f06-acf1-a0e0385641b6", "is_human": true, "event": "Position", "u": 0.4307, "v": 0.616, "ts": 1770}, {"user_id": "24bd210d-3b53-4f06-acf1-a0e0385641b6", "is_human": true, "event": "Position", "u": 0.426, "v": 0.6147, "ts": 1770}, {"user_id": "24bd210d-3b53-4f06-acf1-a0e0385641b6", "is_human": true, "event": "Position", "u": 0.4337, "v": 0.6311, "ts": 1770}, {"user_id": "24bd210d-3b53-4f06-acf1-a0e0385641b6", "is_human": true, "event": "Position", "u": 0.4242, "v": 0.6193, "ts": 1770}, {"user_id": "24bd210d-3b53-4f06-acf1-a0e0385641b6", "is_human": true, "event": "BotKill", "u": 0.421, "v": 0.619, "ts": 1770}, {"user_id": "24bd210d-3b53-4f06-acf1-a0e0385641b6", "is_human": true, "event": "Position", "u": 0.421, "v": 0.619, "ts": 1770}, {"user_id": "24bd210d-3b53-4f06-acf1-a0e0385641b6", "is_human": true, "event": "BotKill", "u": 0.421, "v": 0.619, "ts": 1770}, {"user_id": "24bd210d-3b53-4f06-acf1-a0e0385641b6", "is_human": true, "event": "BotKill", "u": 0.421, "v": 0.619, "ts": 1770}, {"user_id": "24bd210d-3b53-4f06-acf1-a0e0385641b6", "is_human": true, "event": "BotKill", "u": 0.421, "v": 0.619, "ts": 1770}, {"user_id": "24bd210d-3b53-4f06-acf1-a0e0385641b6", "is_human": true, "event": "BotKill", "u": 0.421, "v": 0.619, "ts": 1770}, {"user_id": "24bd210d-3b53-4f06-acf1-a0e0385641b6", "is_human": true, "event": "BotKill", "u": 0.4234, "v": 0.6192, "ts": 1770}, {"user_id": "24bd210d-3b53-4f06-acf1-a0e0385641b6", "is_human": true, "event": "Loot", "u": 0.4226, "v": 0.619, "ts": 1770}, {"user_id": "24bd210d-3b53-4f06-acf1-a0e0385641b6", "is_human": true, "event": "Loot", "u": 0.4226, "v": 0.619, "ts": 1770}, {"user_id": "24bd210d-3b53-4f06-acf1-a0e0385641b6", "is_human": true, "event": "Position", "u": 0.4232, "v": 0.6189, "ts": 1770}, {"user_id": "24bd210d-3b53-4f06-acf1-a0e0385641b6", "is_human": true, "event": "Position", "u": 0.4325, "v": 0.6166, "ts": 1770}, {"user_id": "24bd210d-3b53-4f06-acf1-a0e0385641b6", "is_human": true, "event": "Loot", "u": 0.4325, "v": 0.6166, "ts": 1770}, {"user_id": "24bd210d-3b53-4f06-acf1-a0e0385641b6", "is_human": true, "event": "Loot", "u": 0.4325, "v": 0.6166, "ts": 1770}, {"user_id": "24bd210d-3b53-4f06-acf1-a0e0385641b6", "is_human": true, "event": "Loot", "u": 0.4325, "v": 0.6166, "ts": 1770}, {"user_id": "24bd210d-3b53-4f06-acf1-a0e0385641b6", "is_human": true, "event": "Position", "u": 0.4284, "v": 0.621, "ts": 1770}, {"user_id": "24bd210d-3b53-4f06-acf1-a0e0385641b6", "is_human": true, "event": "BotKill", "u": 0.4284, "v": 0.621, "ts": 1770}, {"user_id": "24bd210d-3b53-4f06-acf1-a0e0385641b6", "is_human": true, "event": "BotKill", "u": 0.4284, "v": 0.621, "ts": 1770}, {"user_id": "24bd210d-3b53-4f06-acf1-a0e0385641b6", "is_human": true, "event": "BotKill", "u": 0.4307, "v": 0.6189, "ts": 1770}, {"user_id": "24bd210d-3b53-4f06-acf1-a0e0385641b6", "is_human": true, "event": "Loot", "u": 0.4352, "v": 0.6175, "ts": 1770}, {"user_id": "24bd210d-3b53-4f06-acf1-a0e0385641b6", "is_human": true, "event": "Loot", "u": 0.4352, "v": 0.6175, "ts": 1770}, {"user_id": "24bd210d-3b53-4f06-acf1-a0e0385641b6", "is_human": true, "event": "Position", "u": 0.4352, "v": 0.6175, "ts": 1770}, {"user_id": "24bd210d-3b53-4f06-acf1-a0e0385641b6", "is_human": true, "event": "Position", "u": 0.4316, "v": 0.6225, "ts": 1770}, {"user_id": "24bd210d-3b53-4f06-acf1-a0e0385641b6", "is_human": true, "event": "Loot", "u": 0.4319, "v": 0.6286, "ts": 1770}, {"user_id": "24bd210d-3b53-4f06-acf1-a0e0385641b6", "is_human": true, "event": "Loot", "u": 0.4319, "v": 0.6286, "ts": 1770}, {"user_id": "24bd210d-3b53-4f06-acf1-a0e0385641b6", "is_human": true, "event": "Position", "u": 0.4319, "v": 0.6286, "ts": 1770}, {"user_id": "24bd210d-3b53-4f06-acf1-a0e0385641b6", "is_human": true, "event": "Position", "u": 0.4446, "v": 0.6302, "ts": 1770}, {"user_id": "24bd210d-3b53-4f06-acf1-a0e0385641b6", "is_human": true, "event": "Position", "u": 0.45, "v": 0.6317, "ts": 1770}, {"user_id": "24bd210d-3b53-4f06-acf1-a0e0385641b6", "is_human": true, "event": "Position", "u": 0.4639, "v": 0.6516, "ts": 1770}, {"user_id": "24bd210d-3b53-4f06-acf1-a0e0385641b6", "is_human": true, "event": "Position", "u": 0.4483, "v": 0.6916, "ts": 1770}, {"user_id": "24bd210d-3b53-4f06-acf1-a0e0385641b6", "is_human": true, "event": "Position", "u": 0.4248, "v": 0.7189, "ts": 1770}, {"user_id": "24bd210d-3b53-4f06-acf1-a0e0385641b6", "is_human": true, "event": "Position", "u": 0.4279, "v": 0.7066, "ts": 1770}, {"user_id": "24bd210d-3b53-4f06-acf1-a0e0385641b6", "is_human": true, "event": "Position", "u": 0.4065, "v": 0.6972, "ts": 1770}, {"user_id": "24bd210d-3b53-4f06-acf1-a0e0385641b6", "is_human": true, "event": "Position", "u": 0.3824, "v": 0.6951, "ts": 1770}, {"user_id": "24bd210d-3b53-4f06-acf1-a0e0385641b6", "is_human": true, "event": "Position", "u": 0.3626, "v": 0.6958, "ts": 1770}, {"user_id": "24bd210d-3b53-4f06-acf1-a0e0385641b6", "is_human": true, "event": "BotKill", "u": 0.3639, "v": 0.6953, "ts": 1770}, {"user_id": "24bd210d-3b53-4f06-acf1-a0e0385641b6", "is_human": true, "event": "Position", "u": 0.3576, "v": 0.7056, "ts": 1770}, {"user_id": "24bd210d-3b53-4f06-acf1-a0e0385641b6", "is_human": true, "event": "Position", "u": 0.3634, "v": 0.7274, "ts": 1770}, {"user_id": "24bd210d-3b53-4f06-acf1-a0e0385641b6", "is_human": true, "event": "Loot", "u": 0.3645, "v": 0.7311, "ts": 1770}, {"user_id": "24bd210d-3b53-4f06-acf1-a0e0385641b6", "is_human": true, "event": "Loot", "u": 0.3645, "v": 0.7311, "ts": 1770}, {"user_id": "24bd210d-3b53-4f06-acf1-a0e0385641b6", "is_human": true, "event": "Position", "u": 0.346, "v": 0.7241, "ts": 1770}, {"user_id": "24bd210d-3b53-4f06-acf1-a0e0385641b6", "is_human": true, "event": "Position", "u": 0.2996, "v": 0.7231, "ts": 1770}, {"user_id": "24bd210d-3b53-4f06-acf1-a0e0385641b6", "is_human": true, "event": "Position", "u": 0.2537, "v": 0.7411, "ts": 1770}, {"user_id": "24bd210d-3b53-4f06-acf1-a0e0385641b6", "is_human": true, "event": "Position", "u": 0.2424, "v": 0.7465, "ts": 1770}]}