{"match_id": "464143e5-ba15-43a6-a331-3fe08d58ad7a", "map_id": "AmbroseValley", "date": "2026-02-12", "human_count": 1, "bot_count": 0, "event_counts": {"Position": 81, "Loot": 19, "BotKill": 2}, "events": [{"user_id": "a36a237e-d4db-447c-9bea-396afe2d275b", "is_human": true, "event": "Position", "u": 0.2523, "v": 0.3103, "ts": 1770}, {"user_id": "a36a237e-d4db-447c-9bea-396afe2d275b", "is_human": true, "event": "Position", "u": 0.2517, "v": 0.3153, "ts": 1770}, {"user_id": "a36a237e-d4db-447c-9bea-396afe2d275b", "is_human": true, "event": "Loot", "u": 0.2533, "v": 0.32, "ts": 1770}, {"user_id": "a36a237e-d4db-447c-9bea-396afe2d275b", "is_human": true, "event": "Loot", "u": 0.2533, "v": 0.32, "ts": 1770}, {"user_id": "a36a237e-d4db-447c-9bea-396afe2d275b", "is_human": true, "event": "Position", "u": 0.2556, "v": 0.3204, "ts": 1770}, {"user_id": "a36a237e-d4db-447c-9bea-396afe2d275b", "is_human": true, "event": "Position", "u": 0.2537, "v": 0.3366, "ts": 1770}, {"user_id": "a36a237e-d4db-447c-9bea-396afe2d275b", "is_human": true, "event": "Position", "u": 0.2521, "v": 0.3367, "ts": 1770}, {"user_id": "a36a237e-d4db-447c-9bea-396afe2d275b", "is_human": true, "event": "Position", "u": 0.2281, "v": 0.3305, "ts": 1770}, {"user_id": "a36a237e-d4db-447c-9bea-396afe2d275b", "is_human": true, "event": "Position", "u": 0.2214, "v": 0.308, "ts": 1770}, {"user_id": "a36a237e-d4db-447c-9bea-396afe2d275b", "is_human": true, "event": "Position", "u": 0.2246, "v": 0.2824, "ts": 1770}, {"user_id": "a36a237e-d4db-447c-9bea-396afe2d275b", "is_human": true, "event": "Position", "u": 0.2288, "v": 0.2717, "ts": 1770}, {"user_id": "a36a237e-d4db-447c-9bea-396afe2d275b", "is_human": true, "event": "Loot", "u": 0.2288, "v": 0.2717, "ts": 1770}, {"user_id": "a36a237e-d4db-447c-9bea-396afe2d275b", "is_human": true, "event": "Position", "u": 0.2271, "v": 0.2697, "ts": 1770}, {"user_id": "a36a237e-d4db-447c-9bea-396afe2d275b", "is_human": true, "event": "Position", "u": 0.2246, "v": 0.2734, "ts": 1770}, {"user_id": "a36a237e-d4db-447c-9bea-396afe2d275b", "is_human": true, "event": "Position", "u": 0.2292, "v": 0.2677, "ts": 1770}, {"user_id": "a36a237e-d4db-447c-9bea-396afe2d275b", "is_human": true, "event": "Position", "u": 0.2289, "v": 0.2632, "ts": 1770}, {"user_id": "a36a237e-d4db-447c-9bea-396afe2d275b", "is_human": true, "event": "Position", "u": 0.2348, "v": 0.2587, "ts": 1770}, {"user_id": "a36a237e-d4db-447c-9bea-396afe2d275b", "is_human": true, "event": "Position", "u": 0.233, "v": 0.2587, "ts": 1770}, {"user_id": "a36a237e-d4db-447c-9bea-396afe2d275b", "is_human": true, "event": "Position", "u": 0.2291, "v": 0.2415, "ts": 1770}, {"user_id": "a36a237e-d4db-447c-9bea-396afe2d275b", "is_human": true, "event": "Position", "u": 0.2293, "v": 0.2108, "ts": 1770}, {"user_id": "a36a237e-d4db-447c-9bea-396afe2d275b", "is_human": true, "event": "Position", "u": 0.231, "v": 0.1843, "ts": 1770}, {"user_id": "a36a237e-d4db-447c-9bea-396afe2d275b", "is_human": true, "event": "Position", "u": 0.2232, "v": 0.1764, "ts": 1770}, {"user_id": "a36a237e-d4db-447c-9bea-396afe2d275b", "is_human": true, "event": "Position", "u": 0.2249, "v": 0.1598, "ts": 1770}, {"user_id": "a36a237e-d4db-447c-9bea-396afe2d275b", "is_human": true, "event": "BotKill", "u": 0.2254, "v": 0.1586, "ts": 1770}, {"user_id": "a36a237e-d4db-447c-9bea-396afe2d275b", "is_human": true, "event": "Position", "u": 0.2253, "v": 0.1582, "ts": 1770}, {"user_id": "a36a237e-d4db-447c-9bea-396afe2d275b", "is_human": true, "event": "Position", "u": 0.2254, "v": 0.1682, "ts": 1770}, {"user_id": "a36a237e-d4db-447c-9bea-396afe2d275b", "is_human": true, "event": "Loot", "u": 0.2255, "v": 0.1679, "ts": 1770}, {"user_id": "a36a237e-d4db-447c-9bea-396afe2d275b", "is_human": true, "event": "Loot", "u": 0.2255, "v": 0.1679, "ts": 1770}, {"user_id": "a36a237e-d4db-447c-9bea-396afe2d275b", "is_human": true, "event": "Position", "u": 0.2189, "v": 0.1688, "ts": 1770}, {"user_id": "a36a237e-d4db-447c-9bea-396afe2d275b", "is_human": true, "event": "Position", "u": 0.2062, "v": 0.1631, "ts": 1770}, {"user_id": "a36a237e-d4db-447c-9bea-396afe2d275b", "is_human": true, "event": "Position", "u": 0.2067, "v": 0.1665, "ts": 1770}, {"user_id": "a36a237e-d4db-447c-9bea-396afe2d275b", "is_human": true, "event": "Position", "u": 0.212, "v": 0.1674, "ts": 1770}, {"user_id": "a36a237e-d4db-447c-9bea-396afe2d275b", "is_human": true, "event": "Position", "u": 0.2104, "v": 0.1674, "ts": 1770}, {"user_id": "a36a237e-d4db-447c-9bea-396afe2d275b", "is_human": true, "event": "Position", "u": 0.2039, "v": 0.1668, "ts": 1770}, {"user_id": "a36a237e-d4db-447c-9bea-396afe2d275b", "is_human": true, "event": "Position", "u": 0.1976, "v": 0.161, "ts": 1770}, {"user_id": "a36a237e-d4db-447c-9bea-396afe2d275b", "is_human": true, "event": "Position", "u": 0.1917, "v": 0.1582, "ts": 1770}, {"user_id": "a36a237e-d4db-447c-9bea-396afe2d275b", "is_human": true, "event": "Position", "u": 0.1878, "v": 0.1618, "ts": 1770}, {"user_id": "a36a237e-d4db-447c-9bea-396afe2d275b", "is_human": true, "event": "Position", "u": 0.1807, "v": 0.1633, "ts": 1770}, {"user_id": "a36a237e-d4db-447c-9bea-396afe2d275b", "is_human": true, "event": "Position", "u": 0.1791, "v": 0.1666, "ts": 1770}, {"user_id": "a36a237e-d4db-447c-9bea-396afe2d275b", "is_human": true, "event": "BotKill", "u": 0.1795, "v": 0.1652, "ts": 1770}, {"user_id": "a36a237e-d4db-447c-9bea-396afe2d275b", "is_human": true, "event": "Loot", "u": 0.1784, "v": 0.167, "ts": 1770}, {"user_id": "a36a237e-d4db-447c-9bea-396afe2d275b", "is_human": true, "event": "Loot", "u": 0.1784, "v": 0.167, "ts": 1770}, {"user_id": "a36a237e-d4db-447c-9bea-396afe2d275b", "is_human": true, "event": "Position", "u": 0.1755, "v": 0.1682, "ts": 1770}, {"user_id": "a36a237e-d4db-447c-9bea-396afe2d275b", "is_human": true, "event": "Position", "u": 0.1717, "v": 0.172, "ts": 1770}, {"user_id": "a36a237e-d4db-447c-9bea-396afe2d275b", "is_human": true, "event": "Position", "u": 0.1709, "v": 0.1705, "ts": 1770}, {"user_id": "a36a237e-d4db-447c-9bea-396afe2d275b", "is_human": true, "event": "Position", "u": 0.1678, "v": 0.1588, "ts": 1770}, {"user_id": "a36a237e-d4db-447c-9bea-396afe2d275b", "is_human": true, "event": "Loot", "u": 0.1674, "v": 0.1587, "ts": 1770}, {"user_id": "a36a237e-d4db-447c-9bea-396afe2d275b", "is_human": true, "event": "Position", "u": 0.1691, "v": 0.16, "ts": 1770}, {"user_id": "a36a237e-d4db-447c-9bea-396afe2d275b", "is_human": true, "event": "Position", "u": 0.1726, "v": 0.1663, "ts": 1770}, {"user_id": "a36a237e-d4db-447c-9bea-396afe2d275b", "is_human": true, "event": "Position", "u": 0.1763, "v": 0.179, "ts": 1770}, {"user_id": "a36a237e-d4db-447c-9bea-396afe2d275b", "is_human": true, "event": "Loot", "u": 0.1761, "v": 0.1788, "ts": 1770}, {"user_id": "a36a237e-d4db-447c-9bea-396afe2d275b", "is_human": true, "event": "Position", "u": 0.1931, "v": 0.1813, "ts": 1770}, {"user_id": "a36a237e-d4db-447c-9bea-396afe2d275b", "is_human": true, "event": "Loot", "u": 0.1921, "v": 0.1794, "ts": 1770}, {"user_id": "a36a237e-d4db-447c-9bea-396afe2d275b", "is_human": true, "event": "Position", "u": 0.189, "v": 0.1719, "ts": 1770}, {"user_id": "a36a237e-d4db-447c-9bea-396afe2d275b", "is_human": true, "event": "Position", "u": 0.1742, "v": 0.1466, "ts": 1770}, {"user_id": "a36a237e-d4db-447c-9bea-396afe2d275b", "is_human": true, "event": "Loot", "u": 0.17, "v": 0.1436, "ts": 1770}, {"user_id": "a36a237e-d4db-447c-9bea-396afe2d275b", "is_human": true, "event": "Position", "u": 0.1581, "v": 0.144, "ts": 1770}, {"user_id": "a36a237e-d4db-447c-9bea-396afe2d275b", "is_human": true, "event": "Position", "u": 0.1438, "v": 0.1531, "ts": 1770}, {"user_id": "a36a237e-d4db-447c-9bea-396afe2d275b", "is_human": true, "event": "Loot", "u": 0.1438, "v": 0.1531, "ts": 1770}, {"user_id": "a36a237e-d4db-447c-9bea-396afe2d275b", "is_human": true, "event": "Position", "u": 0.1532, "v": 0.1589, "ts": 1770}, {"user_id": "a36a237e-d4db-447c-9bea-396afe2d275b", "is_human": true, "event": "Loot", "u": 0.1583, "v": 0.1597, "ts": 1770}, {"user_id": "a36a237e-d4db-447c-9bea-396afe2d275b", "is_human": true, "event": "Position", "u": 0.1575, "v": 0.1606, "ts": 1770}, {"user_id": "a36a237e-d4db-447c-9bea-396afe2d275b", "is_human": true, "event": "Position", "u": 0.1754, "v": 0.1723, "ts": 1770}, {"user_id": "a36a237e-d4db-447c-9bea-396afe2d275b", "is_human": true, "event": "Position", "u": 0.1727, "v": 0.18, "ts": 1770}, {"user_id": "a36a237e-d4db-447c-9bea-396afe2d275b", "is_human": true, "event": "Position", "u": 0.1766, "v": 0.1947, "ts": 1770}, {"user_id": "a36a237e-d4db-447c-9bea-396afe2d275b", "is_human": true, "event": "Position", "u": 0.1847, "v": 0.2102, "ts": 1770}, {"user_id": "a36a237e-d4db-447c-9bea-396afe2d275b", "is_human": true, "event": "Position", "u": 0.1882, "v": 0.2637, "ts": 1770}, {"user_id": "a36a237e-d4db-447c-9bea-396afe2d275b", "is_human": true, "event": "Position", "u": 0.2039, "v": 0.2891, "ts": 1770}, {"user_id": "a36a237e-d4db-447c-9bea-396afe2d275b", "is_human": true, "event": "Position", "u": 0.2139, "v": 0.318, "ts": 1770}, {"user_id": "a36a237e-d4db-447c-9bea-396afe2d275b", "is_human": true, "event": "Position", "u": 0.2147, "v": 0.3484, "ts": 1770}, {"user_id": "a36a237e-d4db-447c-9bea-396afe2d275b", "is_human": true, "event": "Position", "u": 0.2179, "v": 0.3727, "ts": 1770}, {"user_id": "a36a237e-d4db-447c-9bea-396afe2d275b", "is_human": true, "event": "Position", "u": 0.2176, "v": 0.3934, "ts": 1770}, {"user_id": "a36a237e-d4db-447c-9bea-396afe2d275b", "is_human": true, "event": "Position", "u": 0.2192, "v": 0.4103, "ts": 1770}, {"user_id": "a36a237e-d4db-447c-9bea-396afe2d275b", "is_human": true, "event": "Position", "u": 0.2104, "v": 0.4399, "ts": 1770}, {"user_id": "a36a237e-d4db-447c-9bea-396afe2d275b", "is_human": true, "event": "Position", "u": 0.1998, "v": 0.4669, "ts": 1770}, {"user_id": "a36a237e-d4db-447c-9bea-396afe2d275b", "is_human": true, "event": "Position", "u": 0.1932, "v": 0.4823, "ts": 1770}, {"user_id": "a36a237e-d4db-447c-9bea-396afe2d275b", "is_human": true, "event": "Position", "u": 0.1872, "v": 0.5064, "ts": 1770}, {"user_id": "a36a237e-d4db-447c-9bea-396afe2d275b", "is_human": true, "event": "Position", "u": 0.1658, "v": 0.5239, "ts": 1770}, {"user_id": "a36a237e-d4db-447c-9bea-396afe2d275b", "is_human": true, "event": "Position", "u": 0.1468, "v": 0.5358, "ts": 1770}, {"user_id": "a36a237e-d4db-447c-9bea-396afe2d275b", "is_human": true, "event": "Position", "u": 0.1467, "v": 0.5529, "ts": 1770}, {"user_id": "a36a237e-d4db-447c-9bea-396afe2d275b", "is_human": true, "event": "Position", "u": 0.1362, "v": 0.5647, "ts": 1770}, {"user_id": "a36a237e-d4db-447c-9bea-396afe2d275b", "is_human": true, "event": "Loot", "u": 0.1309, "v": 0.5692, "ts": 1770}, {"user_id": "a36a237e-d4db-447c-9bea-396afe2d275b", "is_human": true, "event": "Position", "u": 0.1281, "v": 0.5732, "ts": 1770}, {"user_id": "a36a237e-d4db-447c-9bea-396afe2d275b", "is_human": true, "event": "Position", "u": 0.1089, "v": 0.5912, "ts": 1770}, {"user_id": "a36a237e-d4db-447c-9bea-396afe2d275b", "is_human": true, "event": "Position", "u": 0.1017, "v": 0.6009, "ts": 1770}, {"user_id": "a36a237e-d4db-447c-9bea-396afe2d275b", "is_human": true, "event": "Loot", "u": 0.1017, "v": 0.6009, "ts": 1770}, {"user_id": "a36a237e-d4db-447c-9bea-396afe2d275b", "is_human": true, "event": "Loot", "u": 0.103, "v": 0.6036, "ts": 1770}, {"user_id": "a36a237e-d4db-447c-9bea-396afe2d275b", "is_human": true, "event": "Position", "u": 0.103, "v": 0.6036, "ts": 1770}, {"user_id": "a36a237e-d4db-447c-9bea-396afe2d275b", "is_human": true, "event": "Position", "u": 0.088, "v": 0.6012, "ts": 1770}, {"user_id": "a36a237e-d4db-447c-9bea-396afe2d275b", "is_human": true, "event": "Loot", "u": 0.0878, "v": 0.6032, "ts": 1770}, {"user_id": "a36a237e-d4db-447c-9bea-396afe2d275b", "is_human": true, "event": "Position", "u": 0.0938, "v": 0.5994, "ts": 1770}, {"user_id": "a36a237e-d4db-447c-9bea-396afe2d275b", "is_human": true, "event": "Position", "u": 0.1017, "v": 0.6108, "ts": 1770}, {"user_id": "a36a237e-d4db-447c-9bea-396afe2d275b", "is_human": true, "event": "Position", "u": 0.0966, "v": 0.6148, "ts": 1770}, {"user_id": "a36a237e-d4db-447c-9bea-396afe2d275b", "is_human": true, "event": "Loot", "u": 0.0932, "v": 0.6146, "ts": 1770}, {"user_id": "a36a237e-d4db-447c-9bea-396afe2d275b", "is_human": true, "event": "Position", "u": 0.0934, "v": 0.6115, "ts": 1770}, {"user_id": "a36a237e-d4db-447c-9bea-396afe2d275b", "is_human": true, "event": "Loot", "u": 0.0937, "v": 0.6104, "ts": 1770}, {"user_id": "a36a237e-d4db-447c-9bea-396afe2d275b", "is_human": true, "event": "Position", "u": 0.0957, "v": 0.6181, "ts": 1770}, {"user_id": "a36a237e-d4db-447c-9bea-396afe2d275b", "is_human": true, "event": "Position", "u": 0.1127, "v": 0.6289, "ts": 1770}, {"user_id": "a36a237e-d4db-447c-9bea-396afe2d275b", "is_human": true, "event": "Position", "u": 0.1208, "v": 0.6219, "ts": 1770}, {"user_id": "a36a237e-d4db-447c-9bea-396afe2d275b", "is_human": true, "event": "Position", "u": 0.1446, "v": 0.613, "ts": 1770}, {"user_id": "a36a237e-d4db-447c-9bea-396afe2d275b", "is_human": true, "event": "Position", "u": 0.1481, "v": 0.5909, "ts": 1770}, {"user_id": "a36a237e-d4db-447c-9bea-396afe2d275b", "is_human": true, "event": "Position", "u": 0.1456, "v": 0.5848, "ts": 1770}]}