{"match_id": "78ec7664-4d84-4c21-9ea7-097ca2b06a65", "map_id": "AmbroseValley", "date": "2026-02-13", "human_count": 1, "bot_count": 0, "event_counts": {"Position": 50, "Loot": 12, "BotKill": 1}, "events": [{"user_id": "748892a8-0d0e-40ab-8b16-a34c6d5c413d", "is_human": true, "event": "Position", "u": 0.672, "v": 0.7623, "ts": 1770}, {"user_id": "748892a8-0d0e-40ab-8b16-a34c6d5c413d", "is_human": true, "event": "Position", "u": 0.6642, "v": 0.7466, "ts": 1770}, {"user_id": "748892a8-0d0e-40ab-8b16-a34c6d5c413d", "is_human": true, "event": "Position", "u": 0.6558, "v": 0.7456, "ts": 1770}, {"user_id": "748892a8-0d0e-40ab-8b16-a34c6d5c413d", "is_human": true, "event": "Position", "u": 0.628, "v": 0.7499, "ts": 1770}, {"user_id": "748892a8-0d0e-40ab-8b16-a34c6d5c413d", "is_human": true, "event": "Loot", "u": 0.6275, "v": 0.7498, "ts": 1770}, {"user_id": "748892a8-0d0e-40ab-8b16-a34c6d5c413d", "is_human": true, "event": "Position", "u": 0.6235, "v": 0.7509, "ts": 1770}, {"user_id": "748892a8-0d0e-40ab-8b16-a34c6d5c413d", "is_human": true, "event": "Position", "u": 0.6045, "v": 0.7276, "ts": 1770}, {"user_id": "748892a8-0d0e-40ab-8b16-a34c6d5c413d", "is_human": true, "event": "Position", "u": 0.5936, "v": 0.6954, "ts": 1770}, {"user_id": "748892a8-0d0e-40ab-8b16-a34c6d5c413d", "is_human": true, "event": "Loot", "u": 0.5877, "v": 0.6845, "ts": 1770}, {"user_id": "748892a8-0d0e-40ab-8b16-a34c6d5c413d", "is_human": true, "event": "Loot", "u": 0.5877, "v": 0.6845, "ts": 1770}, {"user_id": "748892a8-0d0e-40ab-8b16-a34c6d5c413d", "is_human": true, "event": "Position", "u": 0.5878, "v": 0.6845, "ts": 1770}, {"user_id": "748892a8-0d0e-40ab-8b16-a34c6d5c413d", "is_human": true, "event": "Position", "u": 0.5871, "v": 0.6574, "ts": 1770}, {"user_id": "748892a8-0d0e-40ab-8b16-a34c6d5c413d", "is_human": true, "event": "Position", "u": 0.5836, "v": 0.6283, "ts": 1770}, {"user_id": "748892a8-0d0e-40ab-8b16-a34c6d5c413d", "is_human": true, "event": "Position", "u": 0.5945, "v": 0.6188, "ts": 1770}, {"user_id": "748892a8-0d0e-40ab-8b16-a34c6d5c413d", "is_human": true, "event": "Loot", "u": 0.5978, "v": 0.6183, "ts": 1770}, {"user_id": "748892a8-0d0e-40ab-8b16-a34c6d5c413d", "is_human": true, "event": "Position", "u": 0.6054, "v": 0.6115, "ts": 1770}, {"user_id": "748892a8-0d0e-40ab-8b16-a34c6d5c413d", "is_human": true, "event": "Loot", "u": 0.613, "v": 0.613, "ts": 1770}, {"user_id": "748892a8-0d0e-40ab-8b16-a34c6d5c413d", "is_human": true, "event": "Position", "u": 0.613, "v": 0.613, "ts": 1770}, {"user_id": "748892a8-0d0e-40ab-8b16-a34c6d5c413d", "is_human": true, "event": "Position", "u": 0.601, "v": 0.6127, "ts": 1770}, {"user_id": "748892a8-0d0e-40ab-8b16-a34c6d5c413d", "is_human": true, "event": "Loot", "u": 0.6003, "v": 0.6124, "ts": 1770}, {"user_id": "748892a8-0d0e-40ab-8b16-a34c6d5c413d", "is_human": true, "event": "Position", "u": 0.6069, "v": 0.6071, "ts": 1770}, {"user_id": "748892a8-0d0e-40ab-8b16-a34c6d5c413d", "is_human": true, "event": "Position", "u": 0.6091, "v": 0.5905, "ts": 1770}, {"user_id": "748892a8-0d0e-40ab-8b16-a34c6d5c413d", "is_human": true, "event": "Position", "u": 0.5927, "v": 0.6087, "ts": 1770}, {"user_id": "748892a8-0d0e-40ab-8b16-a34c6d5c413d", "is_human": true, "event": "Position", "u": 0.6005, "v": 0.5986, "ts": 1770}, {"user_id": "748892a8-0d0e-40ab-8b16-a34c6d5c413d", "is_human": true, "event": "BotKill", "u": 0.5977, "v": 0.6026, "ts": 1770}, {"user_id": "748892a8-0d0e-40ab-8b16-a34c6d5c413d", "is_human": true, "event": "Loot", "u": 0.5968, "v": 0.6034, "ts": 1770}, {"user_id": "748892a8-0d0e-40ab-8b16-a34c6d5c413d", "is_human": true, "event": "Loot", "u": 0.5968, "v": 0.6034, "ts": 1770}, {"user_id": "748892a8-0d0e-40ab-8b16-a34c6d5c413d", "is_human": true, "event": "Position", "u": 0.5968, "v": 0.6034, "ts": 1770}, {"user_id": "748892a8-0d0e-40ab-8b16-a34c6d5c413d", "is_human": true, "event": "Position", "u": 0.5997, "v": 0.6015, "ts": 1770}, {"user_id": "748892a8-0d0e-40ab-8b16-a34c6d5c413d", "is_human": true, "event": "Position", "u": 0.62, "v": 0.5746, "ts": 1770}, {"user_id": "748892a8-0d0e-40ab-8b16-a34c6d5c413d", "is_human": true, "event": "Position", "u": 0.6499, "v": 0.5677, "ts": 1770}, {"user_id": "748892a8-0d0e-40ab-8b16-a34c6d5c413d", "is_human": true, "event": "Position", "u": 0.6737, "v": 0.5453, "ts": 1770}, {"user_id": "748892a8-0d0e-40ab-8b16-a34c6d5c413d", "is_human": true, "event": "Position", "u": 0.6759, "v": 0.5205, "ts": 1770}, {"user_id": "748892a8-0d0e-40ab-8b16-a34c6d5c413d", "is_human": true, "event": "Position", "u": 0.675, "v": 0.4958, "ts": 1770}, {"user_id": "748892a8-0d0e-40ab-8b16-a34c6d5c413d", "is_human": true, "event": "Position", "u": 0.6808, "v": 0.4669, "ts": 1770}, {"user_id": "748892a8-0d0e-40ab-8b16-a34c6d5c413d", "is_human": true, "event": "Position", "u": 0.6731, "v": 0.4341, "ts": 1770}, {"user_id": "748892a8-0d0e-40ab-8b16-a34c6d5c413d", "is_human": true, "event": "Position", "u": 0.6578, "v": 0.4109, "ts": 1770}, {"user_id": "748892a8-0d0e-40ab-8b16-a34c6d5c413d", "is_human": true, "event": "Position", "u": 0.6527, "v": 0.4112, "ts": 1770}, {"user_id": "748892a8-0d0e-40ab-8b16-a34c6d5c413d", "is_human": true, "event": "Position", "u": 0.6658, "v": 0.3814, "ts": 1770}, {"user_id": "748892a8-0d0e-40ab-8b16-a34c6d5c413d", "is_human": true, "event": "Position", "u": 0.6491, "v": 0.3554, "ts": 1770}, {"user_id": "748892a8-0d0e-40ab-8b16-a34c6d5c413d", "is_human": true, "event": "Position", "u": 0.6336, "v": 0.3393, "ts": 1770}, {"user_id": "748892a8-0d0e-40ab-8b16-a34c6d5c413d", "is_human": true, "event": "Position", "u": 0.6239, "v": 0.31, "ts": 1770}, {"user_id": "748892a8-0d0e-40ab-8b16-a34c6d5c413d", "is_human": true, "event": "Position", "u": 0.6214, "v": 0.3037, "ts": 1770}, {"user_id": "748892a8-0d0e-40ab-8b16-a34c6d5c413d", "is_human": true, "event": "Position", "u": 0.6056, "v": 0.2742, "ts": 1770}, {"user_id": "748892a8-0d0e-40ab-8b16-a34c6d5c413d", "is_human": true, "event": "Position", "u": 0.5966, "v": 0.2429, "ts": 1770}, {"user_id": "748892a8-0d0e-40ab-8b16-a34c6d5c413d", "is_human": true, "event": "Position", "u": 0.5924, "v": 0.2182, "ts": 1770}, {"user_id": "748892a8-0d0e-40ab-8b16-a34c6d5c413d", "is_human": true, "event": "Position", "u": 0.6052, "v": 0.1993, "ts": 1770}, {"user_id": "748892a8-0d0e-40ab-8b16-a34c6d5c413d", "is_human": true, "event": "Position", "u": 0.6073, "v": 0.1936, "ts": 1770}, {"user_id": "748892a8-0d0e-40ab-8b16-a34c6d5c413d", "is_human": true, "event": "Loot", "u": 0.6074, "v": 0.1925, "ts": 1770}, {"user_id": "748892a8-0d0e-40ab-8b16-a34c6d5c413d", "is_human": true, "event": "Position", "u": 0.5932, "v": 0.1954, "ts": 1770}, {"user_id": "748892a8-0d0e-40ab-8b16-a34c6d5c413d", "is_human": true, "event": "Loot", "u": 0.5932, "v": 0.1954, "ts": 1770}, {"user_id": "748892a8-0d0e-40ab-8b16-a34c6d5c413d", "is_human": true, "event": "Position", "u": 0.5867, "v": 0.1967, "ts": 1770}, {"user_id": "748892a8-0d0e-40ab-8b16-a34c6d5c413d", "is_human": true, "event": "Position", "u": 0.5809, "v": 0.1985, "ts": 1770}, {"user_id": "748892a8-0d0e-40ab-8b16-a34c6d5c413d", "is_human": true, "event": "Position", "u": 0.5643, "v": 0.1994, "ts": 1770}, {"user_id": "748892a8-0d0e-40ab-8b16-a34c6d5c413d", "is_human": true, "event": "Position", "u": 0.5386, "v": 0.2033, "ts": 1770}, {"user_id": "748892a8-0d0e-40ab-8b16-a34c6d5c413d", "is_human": true, "event": "Position", "u": 0.5205, "v": 0.205, "ts": 1770}, {"user_id": "748892a8-0d0e-40ab-8b16-a34c6d5c413d", "is_human": true, "event": "Position", "u": 0.5272, "v": 0.2113, "ts": 1770}, {"user_id": "748892a8-0d0e-40ab-8b16-a34c6d5c413d", "is_human": true, "event": "Position", "u": 0.5182, "v": 0.223, "ts": 1770}, {"user_id": "748892a8-0d0e-40ab-8b16-a34c6d5c413d", "is_human": true, "event": "Loot", "u": 0.518, "v": 0.2233, "ts": 1770}, {"user_id": "748892a8-0d0e-40ab-8b16-a34c6d5c413d", "is_human": true, "event": "Loot", "u": 0.518, "v": 0.2233, "ts": 1770}, {"user_id": "748892a8-0d0e-40ab-8b16-a34c6d5c413d", "is_human": true, "event": "Position", "u": 0.5145, "v": 0.2229, "ts": 1770}, {"user_id": "748892a8-0d0e-40ab-8b16-a34c6d5c413d", "is_human": true, "event": "Position", "u": 0.5225, "v": 0.2218, "ts": 1770}, {"user_id": "748892a8-0d0e-40ab-8b16-a34c6d5c413d", "is_human": true, "event": "Position", "u": 0.5342, "v": 0.2227, "ts": 1770}]}