{"match_id": "988efa5d-2211-482b-8906-c05378651c5e", "map_id": "AmbroseValley", "date": "2026-02-11", "human_count": 1, "bot_count": 0, "event_counts": {"Position": 59, "Loot": 22, "BotKill": 6}, "events": [{"user_id": "5d5c53aa-5cc4-4e9d-abad-decc2991753e", "is_human": true, "event": "Position", "u": 0.7083, "v": 0.4759, "ts": 1770}, {"user_id": "5d5c53aa-5cc4-4e9d-abad-decc2991753e", "is_human": true, "event": "Position", "u": 0.6952, "v": 0.4617, "ts": 1770}, {"user_id": "5d5c53aa-5cc4-4e9d-abad-decc2991753e", "is_human": true, "event": "Position", "u": 0.6974, "v": 0.4446, "ts": 1770}, {"user_id": "5d5c53aa-5cc4-4e9d-abad-decc2991753e", "is_human": true, "event": "Position", "u": 0.6823, "v": 0.4329, "ts": 1770}, {"user_id": "5d5c53aa-5cc4-4e9d-abad-decc2991753e", "is_human": true, "event": "Position", "u": 0.6573, "v": 0.433, "ts": 1770}, {"user_id": "5d5c53aa-5cc4-4e9d-abad-decc2991753e", "is_human": true, "event": "Position", "u": 0.6416, "v": 0.4328, "ts": 1770}, {"user_id": "5d5c53aa-5cc4-4e9d-abad-decc2991753e", "is_human": true, "event": "Position", "u": 0.6283, "v": 0.433, "ts": 1770}, {"user_id": "5d5c53aa-5cc4-4e9d-abad-decc2991753e", "is_human": true, "event": "Position", "u": 0.6098, "v": 0.4284, "ts": 1770}, {"user_id": "5d5c53aa-5cc4-4e9d-abad-decc2991753e", "is_human": true, "event": "Position", "u": 0.5896, "v": 0.4371, "ts": 1770}, {"user_id": "5d5c53aa-5cc4-4e9d-abad-decc2991753e", "is_human": true, "event": "Position", "u": 0.5842, "v": 0.4463, "ts": 1770}, {"user_id": "5d5c53aa-5cc4-4e9d-abad-decc2991753e", "is_human": true, "event": "Loot", "u": 0.5784, "v": 0.4519, "ts": 1770}, {"user_id": "5d5c53aa-5cc4-4e9d-abad-decc2991753e", "is_human": true, "event": "Position", "u": 0.5785, "v": 0.4459, "ts": 1770}, {"user_id": "5d5c53aa-5cc4-4e9d-abad-decc2991753e", "is_human": true, "event": "Loot", "u": 0.5782, "v": 0.4434, "ts": 1770}, {"user_id": "5d5c53aa-5cc4-4e9d-abad-decc2991753e", "is_human": true, "event": "Loot", "u": 0.5772, "v": 0.4402, "ts": 1770}, {"user_id": "5d5c53aa-5cc4-4e9d-abad-decc2991753e", "is_human": true, "event": "Loot", "u": 0.5793, "v": 0.4368, "ts": 1770}, {"user_id": "5d5c53aa-5cc4-4e9d-abad-decc2991753e", "is_human": true, "event": "Position", "u": 0.5793, "v": 0.4368, "ts": 1770}, {"user_id": "5d5c53aa-5cc4-4e9d-abad-decc2991753e", "is_human": true, "event": "Position", "u": 0.5763, "v": 0.4488, "ts": 1770}, {"user_id": "5d5c53aa-5cc4-4e9d-abad-decc2991753e", "is_human": true, "event": "Position", "u": 0.5671, "v": 0.434, "ts": 1770}, {"user_id": "5d5c53aa-5cc4-4e9d-abad-decc2991753e", "is_human": true, "event": "Position", "u": 0.5655, "v": 0.4286, "ts": 1770}, {"user_id": "5d5c53aa-5cc4-4e9d-abad-decc2991753e", "is_human": true, "event": "Position", "u": 0.5749, "v": 0.4266, "ts": 1770}, {"user_id": "5d5c53aa-5cc4-4e9d-abad-decc2991753e", "is_human": true, "event": "Loot", "u": 0.5751, "v": 0.4265, "ts": 1770}, {"user_id": "5d5c53aa-5cc4-4e9d-abad-decc2991753e", "is_human": true, "event": "Loot", "u": 0.5766, "v": 0.4201, "ts": 1770}, {"user_id": "5d5c53aa-5cc4-4e9d-abad-decc2991753e", "is_human": true, "event": "Position", "u": 0.5785, "v": 0.4201, "ts": 1770}, {"user_id": "5d5c53aa-5cc4-4e9d-abad-decc2991753e", "is_human": true, "event": "Loot", "u": 0.5719, "v": 0.4219, "ts": 1770}, {"user_id": "5d5c53aa-5cc4-4e9d-abad-decc2991753e", "is_human": true, "event": "Loot", "u": 0.5696, "v": 0.4225, "ts": 1770}, {"user_id": "5d5c53aa-5cc4-4e9d-abad-decc2991753e", "is_human": true, "event": "Position", "u": 0.5697, "v": 0.4228, "ts": 1770}, {"user_id": "5d5c53aa-5cc4-4e9d-abad-decc2991753e", "is_human": true, "event": "Position", "u": 0.5536, "v": 0.4144, "ts": 1770}, {"user_id": "5d5c53aa-5cc4-4e9d-abad-decc2991753e", "is_human": true, "event": "Position", "u": 0.5442, "v": 0.4135, "ts": 1770}, {"user_id": "5d5c53aa-5cc4-4e9d-abad-decc2991753e", "is_human": true, "event": "Position", "u": 0.5544, "v": 0.412, "ts": 1770}, {"user_id": "5d5c53aa-5cc4-4e9d-abad-decc2991753e", "is_human": true, "event": "Position", "u": 0.5478, "v": 0.4139, "ts": 1770}, {"user_id": "5d5c53aa-5cc4-4e9d-abad-decc2991753e", "is_human": true, "event": "Position", "u": 0.5235, "v": 0.4245, "ts": 1770}, {"user_id": "5d5c53aa-5cc4-4e9d-abad-decc2991753e", "is_human": true, "event": "Position", "u": 0.5177, "v": 0.4448, "ts": 1770}, {"user_id": "5d5c53aa-5cc4-4e9d-abad-decc2991753e", "is_human": true, "event": "Position", "u": 0.5082, "v": 0.4409, "ts": 1770}, {"user_id": "5d5c53aa-5cc4-4e9d-abad-decc2991753e", "is_human": true, "event": "Loot", "u": 0.5082, "v": 0.4409, "ts": 1770}, {"user_id": "5d5c53aa-5cc4-4e9d-abad-decc2991753e", "is_human": true, "event": "Position", "u": 0.5096, "v": 0.4357, "ts": 1770}, {"user_id": "5d5c53aa-5cc4-4e9d-abad-decc2991753e", "is_human": true, "event": "Loot", "u": 0.5096, "v": 0.4357, "ts": 1770}, {"user_id": "5d5c53aa-5cc4-4e9d-abad-decc2991753e", "is_human": true, "event": "Position", "u": 0.5013, "v": 0.425, "ts": 1770}, {"user_id": "5d5c53aa-5cc4-4e9d-abad-decc2991753e", "is_human": true, "event": "Position", "u": 0.5002, "v": 0.4299, "ts": 1770}, {"user_id": "5d5c53aa-5cc4-4e9d-abad-decc2991753e", "is_human": true, "event": "Position", "u": 0.5008, "v": 0.4448, "ts": 1770}, {"user_id": "5d5c53aa-5cc4-4e9d-abad-decc2991753e", "is_human": true, "event": "Position", "u": 0.5096, "v": 0.4513, "ts": 1770}, {"user_id": "5d5c53aa-5cc4-4e9d-abad-decc2991753e", "is_human": true, "event": "Position", "u": 0.519, "v": 0.4408, "ts": 1770}, {"user_id": "5d5c53aa-5cc4-4e9d-abad-decc2991753e", "is_human": true, "event": "Position", "u": 0.5126, "v": 0.447, "ts": 1770}, {"user_id": "5d5c53aa-5cc4-4e9d-abad-decc2991753e", "is_human": true, "event": "BotKill", "u": 0.5099, "v": 0.4505, "ts": 1770}, {"user_id": "5d5c53aa-5cc4-4e9d-abad-decc2991753e", "is_human": true, "event": "Position", "u": 0.5116, "v": 0.4497, "ts": 1770}, {"user_id": "5d5c53aa-5cc4-4e9d-abad-decc2991753e", "is_human": true, "event": "Position", "u": 0.51, "v": 0.4499, "ts": 1770}, {"user_id": "5d5c53aa-5cc4-4e9d-abad-decc2991753e", "is_human": true, "event": "BotKill", "u": 0.5099, "v": 0.45, "ts": 1770}, {"user_id": "5d5c53aa-5cc4-4e9d-abad-decc2991753e", "is_human": true, "event": "BotKill", "u": 0.5102, "v": 0.4493, "ts": 1770}, {"user_id": "5d5c53aa-5cc4-4e9d-abad-decc2991753e", "is_human": true, "event": "Loot", "u": 0.5081, "v": 0.4461, "ts": 1770}, {"user_id": "5d5c53aa-5cc4-4e9d-abad-decc2991753e", "is_human": true, "event": "Loot", "u": 0.5081, "v": 0.4461, "ts": 1770}, {"user_id": "5d5c53aa-5cc4-4e9d-abad-decc2991753e", "is_human": true, "event": "Position", "u": 0.5081, "v": 0.4461, "ts": 1770}, {"user_id": "5d5c53aa-5cc4-4e9d-abad-decc2991753e", "is_human": true, "event": "BotKill", "u": 0.5089, "v": 0.4449, "ts": 1770}, {"user_id": "5d5c53aa-5cc4-4e9d-abad-decc2991753e", "is_human": true, "event": "Position", "u": 0.5123, "v": 0.4549, "ts": 1770}, {"user_id": "5d5c53aa-5cc4-4e9d-abad-decc2991753e", "is_human": true, "event": "Loot", "u": 0.5121, "v": 0.4571, "ts": 1770}, {"user_id": "5d5c53aa-5cc4-4e9d-abad-decc2991753e", "is_human": true, "event": "Loot", "u": 0.5121, "v": 0.4571, "ts": 1770}, {"user_id": "5d5c53aa-5cc4-4e9d-abad-decc2991753e", "is_human": true, "event": "Position", "u": 0.5167, "v": 0.4599, "ts": 1770}, {"user_id": "5d5c53aa-5cc4-4e9d-abad-decc2991753e", "is_human": true, "event": "Position", "u": 0.5142, "v": 0.4583, "ts": 1770}, {"user_id": "5d5c53aa-5cc4-4e9d-abad-decc2991753e", "is_human": true, "event": "Position", "u": 0.5134, "v": 0.4604, "ts": 1770}, {"user_id": "5d5c53aa-5cc4-4e9d-abad-decc2991753e", "is_human": true, "event": "Position", "u": 0.5173, "v": 0.4547, "ts": 1770}, {"user_id": "5d5c53aa-5cc4-4e9d-abad-decc2991753e", "is_human": true, "event": "Position", "u": 0.5224, "v": 0.4481, "ts": 1770}, {"user_id": "5d5c53aa-5cc4-4e9d-abad-decc2991753e", "is_human": true, "event": "Position", "u": 0.5127, "v": 0.4533, "ts": 1770}, {"user_id": "5d5c53aa-5cc4-4e9d-abad-decc2991753e", "is_human": true, "event": "Position", "u": 0.5191, "v": 0.4547, "ts": 1770}, {"user_id": "5d5c53aa-5cc4-4e9d-abad-decc2991753e", "is_human": true, "event": "BotKill", "u": 0.5192, "v": 0.4547, "ts": 1770}, {"user_id": "5d5c53aa-5cc4-4e9d-abad-decc2991753e", "is_human": true, "event": "Loot", "u": 0.5209, "v": 0.4503, "ts": 1770}, {"user_id": "5d5c53aa-5cc4-4e9d-abad-decc2991753e", "is_human": true, "event": "Loot", "u": 0.5209, "v": 0.4503, "ts": 1770}, {"user_id": "5d5c53aa-5cc4-4e9d-abad-decc2991753e", "is_human": true, "event": "Loot", "u": 0.5209, "v": 0.4503, "ts": 1770}, {"user_id": "5d5c53aa-5cc4-4e9d-abad-decc2991753e", "is_human": true, "event": "Position", "u": 0.5209, "v": 0.4503, "ts": 1770}, {"user_id": "5d5c53aa-5cc4-4e9d-abad-decc2991753e", "is_human": true, "event": "Loot", "u": 0.5209, "v": 0.4503, "ts": 1770}, {"user_id": "5d5c53aa-5cc4-4e9d-abad-decc2991753e", "is_human": true, "event": "Loot", "u": 0.5209, "v": 0.4503, "ts": 1770}, {"user_id": "5d5c53aa-5cc4-4e9d-abad-decc2991753e", "is_human": true, "event": "Loot", "u": 0.5209, "v": 0.4503, "ts": 1770}, {"user_id": "5d5c53aa-5cc4-4e9d-abad-decc2991753e", "is_human": true, "event": "Position", "u": 0.5212, "v": 0.4476, "ts": 1770}, {"user_id": "5d5c53aa-5cc4-4e9d-abad-decc2991753e", "is_human": true, "event": "Position", "u": 0.5096, "v": 0.448, "ts": 1770}, {"user_id": "5d5c53aa-5cc4-4e9d-abad-decc2991753e", "is_human": true, "event": "Position", "u": 0.5208, "v": 0.4415, "ts": 1770}, {"user_id": "5d5c53aa-5cc4-4e9d-abad-decc2991753e", "is_human": true, "event": "Position", "u": 0.5286, "v": 0.4214, "ts": 1770}, {"user_id": "5d5c53aa-5cc4-4e9d-abad-decc2991753e", "is_human": true, "event": "Position", "u": 0.5402, "v": 0.4052, "ts": 1770}, {"user_id": "5d5c53aa-5cc4-4e9d-abad-decc2991753e", "is_human": true, "event": "Position", "u": 0.5452, "v": 0.3718, "ts": 1770}, {"user_id": "5d5c53aa-5cc4-4e9d-abad-decc2991753e", "is_human": true, "event": "Position", "u": 0.5471, "v": 0.3421, "ts": 1770}, {"user_id": "5d5c53aa-5cc4-4e9d-abad-decc2991753e", "is_human": true, "event": "Position", "u": 0.5459, "v": 0.3195, "ts": 1770}, {"user_id": "5d5c53aa-5cc4-4e9d-abad-decc2991753e", "is_human": true, "event": "Position", "u": 0.5246, "v": 0.2943, "ts": 1770}, {"user_id": "5d5c53aa-5cc4-4e9d-abad-decc2991753e", "is_human": true, "event": "Position", "u": 0.504, "v": 0.2708, "ts": 1770}, {"user_id": "5d5c53aa-5cc4-4e9d-abad-decc2991753e", "is_human": true, "event": "Position", "u": 0.5037, "v": 0.252, "ts": 1770}, {"user_id": "5d5c53aa-5cc4-4e9d-abad-decc2991753e", "is_human": true, "event": "BotKill", "u": 0.5055, "v": 0.2433, "ts": 1770}, {"user_id": "5d5c53aa-5cc4-4e9d-abad-decc2991753e", "is_human": true, "event": "Position", "u": 0.5036, "v": 0.2411, "ts": 1770}, {"user_id": "5d5c53aa-5cc4-4e9d-abad-decc2991753e", "is_human": true, "event": "Loot", "u": 0.5042, "v": 0.2243, "ts": 1770}, {"user_id": "5d5c53aa-5cc4-4e9d-abad-decc2991753e", "is_human": true, "event": "Loot", "u": 0.5042, "v": 0.2243, "ts": 1770}, {"user_id": "5d5c53aa-5cc4-4e9d-abad-decc2991753e", "is_human": true, "event": "Position", "u": 0.5063, "v": 0.2216, "ts": 1770}, {"user_id": "5d5c53aa-5cc4-4e9d-abad-decc2991753e", "is_human": true, "event": "Position", "u": 0.4995, "v": 0.2011, "ts": 1770}, {"user_id": "5d5c53aa-5cc4-4e9d-abad-decc2991753e", "is_human": true, "event": "Position", "u": 0.4923, "v": 0.1822, "ts": 1770}]}