{"match_id": "9951374c-10d4-48a2-8227-a857958781e2", "map_id": "Lockdown", "date": "2026-02-13", "human_count": 1, "bot_count": 0, "event_counts": {"Position": 110, "Loot": 9, "KilledByStorm": 1}, "events": [{"user_id": "b3340cc5-c9fa-4108-b56d-0728bc978a22", "is_human": true, "event": "Position", "u": 0.6382, "v": 0.814, "ts": 1770}, {"user_id": "b3340cc5-c9fa-4108-b56d-0728bc978a22", "is_human": true, "event": "Position", "u": 0.6347, "v": 0.8169, "ts": 1770}, {"user_id": "b3340cc5-c9fa-4108-b56d-0728bc978a22", "is_human": true, "event": "Position", "u": 0.6267, "v": 0.8211, "ts": 1770}, {"user_id": "b3340cc5-c9fa-4108-b56d-0728bc978a22", "is_human": true, "event": "Position", "u": 0.6247, "v": 0.8232, "ts": 1770}, {"user_id": "b3340cc5-c9fa-4108-b56d-0728bc978a22", "is_human": true, "event": "Position", "u": 0.622, "v": 0.8132, "ts": 1770}, {"user_id": "b3340cc5-c9fa-4108-b56d-0728bc978a22", "is_human": true, "event": "Position", "u": 0.6216, "v": 0.8071, "ts": 1770}, {"user_id": "b3340cc5-c9fa-4108-b56d-0728bc978a22", "is_human": true, "event": "Position", "u": 0.6217, "v": 0.8034, "ts": 1770}, {"user_id": "b3340cc5-c9fa-4108-b56d-0728bc978a22", "is_human": true, "event": "Position", "u": 0.6127, "v": 0.8063, "ts": 1770}, {"user_id": "b3340cc5-c9fa-4108-b56d-0728bc978a22", "is_human": true, "event": "Position", "u": 0.6094, "v": 0.8076, "ts": 1770}, {"user_id": "b3340cc5-c9fa-4108-b56d-0728bc978a22", "is_human": true, "event": "Position", "u": 0.6084, "v": 0.8031, "ts": 1770}, {"user_id": "b3340cc5-c9fa-4108-b56d-0728bc978a22", "is_human": true, "event": "Position", "u": 0.6046, "v": 0.8034, "ts": 1770}, {"user_id": "b3340cc5-c9fa-4108-b56d-0728bc978a22", "is_human": true, "event": "Loot", "u": 0.6065, "v": 0.8026, "ts": 1770}, {"user_id": "b3340cc5-c9fa-4108-b56d-0728bc978a22", "is_human": true, "event": "Position", "u": 0.6065, "v": 0.8026, "ts": 1770}, {"user_id": "b3340cc5-c9fa-4108-b56d-0728bc978a22", "is_human": true, "event": "Position", "u": 0.6014, "v": 0.806, "ts": 1770}, {"user_id": "b3340cc5-c9fa-4108-b56d-0728bc978a22", "is_human": true, "event": "Position", "u": 0.5933, "v": 0.808, "ts": 1770}, {"user_id": "b3340cc5-c9fa-4108-b56d-0728bc978a22", "is_human": true, "event": "Loot", "u": 0.5918, "v": 0.8078, "ts": 1770}, {"user_id": "b3340cc5-c9fa-4108-b56d-0728bc978a22", "is_human": true, "event": "Position", "u": 0.6006, "v": 0.8084, "ts": 1770}, {"user_id": "b3340cc5-c9fa-4108-b56d-0728bc978a22", "is_human": true, "event": "Position", "u": 0.6031, "v": 0.8044, "ts": 1770}, {"user_id": "b3340cc5-c9fa-4108-b56d-0728bc978a22", "is_human": true, "event": "Position", "u": 0.6037, "v": 0.7963, "ts": 1770}, {"user_id": "b3340cc5-c9fa-4108-b56d-0728bc978a22", "is_human": true, "event": "Position", "u": 0.6076, "v": 0.79, "ts": 1770}, {"user_id": "b3340cc5-c9fa-4108-b56d-0728bc978a22", "is_human": true, "event": "Position", "u": 0.6024, "v": 0.7872, "ts": 1770}, {"user_id": "b3340cc5-c9fa-4108-b56d-0728bc978a22", "is_human": true, "event": "Position", "u": 0.6007, "v": 0.7835, "ts": 1770}, {"user_id": "b3340cc5-c9fa-4108-b56d-0728bc978a22", "is_human": true, "event": "Position", "u": 0.594, "v": 0.7866, "ts": 1770}, {"user_id": "b3340cc5-c9fa-4108-b56d-0728bc978a22", "is_human": true, "event": "Position", "u": 0.6003, "v": 0.7828, "ts": 1770}, {"user_id": "b3340cc5-c9fa-4108-b56d-0728bc978a22", "is_human": true, "event": "Position", "u": 0.6082, "v": 0.7787, "ts": 1770}, {"user_id": "b3340cc5-c9fa-4108-b56d-0728bc978a22", "is_human": true, "event": "Position", "u": 0.6001, "v": 0.7826, "ts": 1770}, {"user_id": "b3340cc5-c9fa-4108-b56d-0728bc978a22", "is_human": true, "event": "Position", "u": 0.5999, "v": 0.7824, "ts": 1770}, {"user_id": "b3340cc5-c9fa-4108-b56d-0728bc978a22", "is_human": true, "event": "Position", "u": 0.6024, "v": 0.7892, "ts": 1770}, {"user_id": "b3340cc5-c9fa-4108-b56d-0728bc978a22", "is_human": true, "event": "Position", "u": 0.6148, "v": 0.8066, "ts": 1770}, {"user_id": "b3340cc5-c9fa-4108-b56d-0728bc978a22", "is_human": true, "event": "Position", "u": 0.6163, "v": 0.7978, "ts": 1770}, {"user_id": "b3340cc5-c9fa-4108-b56d-0728bc978a22", "is_human": true, "event": "Position", "u": 0.6169, "v": 0.8029, "ts": 1770}, {"user_id": "b3340cc5-c9fa-4108-b56d-0728bc978a22", "is_human": true, "event": "Position", "u": 0.6192, "v": 0.7961, "ts": 1770}, {"user_id": "b3340cc5-c9fa-4108-b56d-0728bc978a22", "is_human": true, "event": "Position", "u": 0.6208, "v": 0.8045, "ts": 1770}, {"user_id": "b3340cc5-c9fa-4108-b56d-0728bc978a22", "is_human": true, "event": "Position", "u": 0.6277, "v": 0.8097, "ts": 1770}, {"user_id": "b3340cc5-c9fa-4108-b56d-0728bc978a22", "is_human": true, "event": "Position", "u": 0.6303, "v": 0.8201, "ts": 1770}, {"user_id": "b3340cc5-c9fa-4108-b56d-0728bc978a22", "is_human": true, "event": "Position", "u": 0.6295, "v": 0.8149, "ts": 1770}, {"user_id": "b3340cc5-c9fa-4108-b56d-0728bc978a22", "is_human": true, "event": "Position", "u": 0.6279, "v": 0.8153, "ts": 1770}, {"user_id": "b3340cc5-c9fa-4108-b56d-0728bc978a22", "is_human": true, "event": "Position", "u": 0.6047, "v": 0.8233, "ts": 1770}, {"user_id": "b3340cc5-c9fa-4108-b56d-0728bc978a22", "is_human": true, "event": "Position", "u": 0.5925, "v": 0.8244, "ts": 1770}, {"user_id": "b3340cc5-c9fa-4108-b56d-0728bc978a22", "is_human": true, "event": "Position", "u": 0.5892, "v": 0.8231, "ts": 1770}, {"user_id": "b3340cc5-c9fa-4108-b56d-0728bc978a22", "is_human": true, "event": "Position", "u": 0.5843, "v": 0.8236, "ts": 1770}, {"user_id": "b3340cc5-c9fa-4108-b56d-0728bc978a22", "is_human": true, "event": "Position", "u": 0.5653, "v": 0.821, "ts": 1770}, {"user_id": "b3340cc5-c9fa-4108-b56d-0728bc978a22", "is_human": true, "event": "Position", "u": 0.5491, "v": 0.8203, "ts": 1770}, {"user_id": "b3340cc5-c9fa-4108-b56d-0728bc978a22", "is_human": true, "event": "Position", "u": 0.5438, "v": 0.8173, "ts": 1770}, {"user_id": "b3340cc5-c9fa-4108-b56d-0728bc978a22", "is_human": true, "event": "Position", "u": 0.5304, "v": 0.8216, "ts": 1770}, {"user_id": "b3340cc5-c9fa-4108-b56d-0728bc978a22", "is_human": true, "event": "Position", "u": 0.5268, "v": 0.8213, "ts": 1770}, {"user_id": "b3340cc5-c9fa-4108-b56d-0728bc978a22", "is_human": true, "event": "Position", "u": 0.5201, "v": 0.8132, "ts": 1770}, {"user_id": "b3340cc5-c9fa-4108-b56d-0728bc978a22", "is_human": true, "event": "Position", "u": 0.5163, "v": 0.809, "ts": 1770}, {"user_id": "b3340cc5-c9fa-4108-b56d-0728bc978a22", "is_human": true, "event": "Position", "u": 0.5117, "v": 0.8003, "ts": 1770}, {"user_id": "b3340cc5-c9fa-4108-b56d-0728bc978a22", "is_human": true, "event": "Position", "u": 0.5115, "v": 0.7999, "ts": 1770}, {"user_id": "b3340cc5-c9fa-4108-b56d-0728bc978a22", "is_human": true, "event": "Position", "u": 0.5169, "v": 0.7969, "ts": 1770}, {"user_id": "b3340cc5-c9fa-4108-b56d-0728bc978a22", "is_human": true, "event": "Position", "u": 0.5346, "v": 0.7919, "ts": 1770}, {"user_id": "b3340cc5-c9fa-4108-b56d-0728bc978a22", "is_human": true, "event": "Position", "u": 0.5351, "v": 0.7909, "ts": 1770}, {"user_id": "b3340cc5-c9fa-4108-b56d-0728bc978a22", "is_human": true, "event": "Position", "u": 0.5356, "v": 0.7897, "ts": 1770}, {"user_id": "b3340cc5-c9fa-4108-b56d-0728bc978a22", "is_human": true, "event": "Position", "u": 0.5399, "v": 0.7902, "ts": 1770}, {"user_id": "b3340cc5-c9fa-4108-b56d-0728bc978a22", "is_human": true, "event": "Loot", "u": 0.5399, "v": 0.7902, "ts": 1770}, {"user_id": "b3340cc5-c9fa-4108-b56d-0728bc978a22", "is_human": true, "event": "Position", "u": 0.5423, "v": 0.7823, "ts": 1770}, {"user_id": "b3340cc5-c9fa-4108-b56d-0728bc978a22", "is_human": true, "event": "Position", "u": 0.5479, "v": 0.7787, "ts": 1770}, {"user_id": "b3340cc5-c9fa-4108-b56d-0728bc978a22", "is_human": true, "event": "Position", "u": 0.5511, "v": 0.7795, "ts": 1770}, {"user_id": "b3340cc5-c9fa-4108-b56d-0728bc978a22", "is_human": true, "event": "Loot", "u": 0.5521, "v": 0.7801, "ts": 1770}, {"user_id": "b3340cc5-c9fa-4108-b56d-0728bc978a22", "is_human": true, "event": "Position", "u": 0.5521, "v": 0.7801, "ts": 1770}, {"user_id": "b3340cc5-c9fa-4108-b56d-0728bc978a22", "is_human": true, "event": "Position", "u": 0.5528, "v": 0.7793, "ts": 1770}, {"user_id": "b3340cc5-c9fa-4108-b56d-0728bc978a22", "is_human": true, "event": "Position", "u": 0.5552, "v": 0.7831, "ts": 1770}, {"user_id": "b3340cc5-c9fa-4108-b56d-0728bc978a22", "is_human": true, "event": "Position", "u": 0.5584, "v": 0.7909, "ts": 1770}, {"user_id": "b3340cc5-c9fa-4108-b56d-0728bc978a22", "is_human": true, "event": "Position", "u": 0.5604, "v": 0.7918, "ts": 1770}, {"user_id": "b3340cc5-c9fa-4108-b56d-0728bc978a22", "is_human": true, "event": "Position", "u": 0.5812, "v": 0.8013, "ts": 1770}, {"user_id": "b3340cc5-c9fa-4108-b56d-0728bc978a22", "is_human": true, "event": "Position", "u": 0.6039, "v": 0.7896, "ts": 1770}, {"user_id": "b3340cc5-c9fa-4108-b56d-0728bc978a22", "is_human": true, "event": "Position", "u": 0.6062, "v": 0.7897, "ts": 1770}, {"user_id": "b3340cc5-c9fa-4108-b56d-0728bc978a22", "is_human": true, "event": "Position", "u": 0.6039, "v": 0.79, "ts": 1770}, {"user_id": "b3340cc5-c9fa-4108-b56d-0728bc978a22", "is_human": true, "event": "Position", "u": 0.6108, "v": 0.8048, "ts": 1770}, {"user_id": "b3340cc5-c9fa-4108-b56d-0728bc978a22", "is_human": true, "event": "Position", "u": 0.6185, "v": 0.8146, "ts": 1770}, {"user_id": "b3340cc5-c9fa-4108-b56d-0728bc978a22", "is_human": true, "event": "Position", "u": 0.6229, "v": 0.8021, "ts": 1770}, {"user_id": "b3340cc5-c9fa-4108-b56d-0728bc978a22", "is_human": true, "event": "Position", "u": 0.6259, "v": 0.7922, "ts": 1770}, {"user_id": "b3340cc5-c9fa-4108-b56d-0728bc978a22", "is_human": true, "event": "Position", "u": 0.6257, "v": 0.7966, "ts": 1770}, {"user_id": "b3340cc5-c9fa-4108-b56d-0728bc978a22", "is_human": true, "event": "Position", "u": 0.6208, "v": 0.7967, "ts": 1770}, {"user_id": "b3340cc5-c9fa-4108-b56d-0728bc978a22", "is_human": true, "event": "Position", "u": 0.64, "v": 0.7918, "ts": 1770}, {"user_id": "b3340cc5-c9fa-4108-b56d-0728bc978a22", "is_human": true, "event": "Position", "u": 0.6413, "v": 0.7843, "ts": 1770}, {"user_id": "b3340cc5-c9fa-4108-b56d-0728bc978a22", "is_human": true, "event": "Position", "u": 0.6388, "v": 0.7597, "ts": 1770}, {"user_id": "b3340cc5-c9fa-4108-b56d-0728bc978a22", "is_human": true, "event": "Position", "u": 0.622, "v": 0.7332, "ts": 1770}, {"user_id": "b3340cc5-c9fa-4108-b56d-0728bc978a22", "is_human": true, "event": "Position", "u": 0.6045, "v": 0.7284, "ts": 1770}, {"user_id": "b3340cc5-c9fa-4108-b56d-0728bc978a22", "is_human": true, "event": "Loot", "u": 0.6042, "v": 0.7273, "ts": 1770}, {"user_id": "b3340cc5-c9fa-4108-b56d-0728bc978a22", "is_human": true, "event": "Position", "u": 0.5973, "v": 0.7407, "ts": 1770}, {"user_id": "b3340cc5-c9fa-4108-b56d-0728bc978a22", "is_human": true, "event": "Loot", "u": 0.5973, "v": 0.7407, "ts": 1770}, {"user_id": "b3340cc5-c9fa-4108-b56d-0728bc978a22", "is_human": true, "event": "Position", "u": 0.5951, "v": 0.7385, "ts": 1770}, {"user_id": "b3340cc5-c9fa-4108-b56d-0728bc978a22", "is_human": true, "event": "Loot", "u": 0.596, "v": 0.7398, "ts": 1770}, {"user_id": "b3340cc5-c9fa-4108-b56d-0728bc978a22", "is_human": true, "event": "Position", "u": 0.5994, "v": 0.734, "ts": 1770}, {"user_id": "b3340cc5-c9fa-4108-b56d-0728bc978a22", "is_human": true, "event": "Position", "u": 0.5939, "v": 0.7223, "ts": 1770}, {"user_id": "b3340cc5-c9fa-4108-b56d-0728bc978a22", "is_human": true, "event": "Position", "u": 0.5898, "v": 0.7318, "ts": 1770}, {"user_id": "b3340cc5-c9fa-4108-b56d-0728bc978a22", "is_human": true, "event": "Position", "u": 0.5843, "v": 0.7386, "ts": 1770}, {"user_id": "b3340cc5-c9fa-4108-b56d-0728bc978a22", "is_human": true, "event": "Loot", "u": 0.5848, "v": 0.7383, "ts": 1770}, {"user_id": "b3340cc5-c9fa-4108-b56d-0728bc978a22", "is_human": true, "event": "Loot", "u": 0.5848, "v": 0.7383, "ts": 1770}, {"user_id": "b3340cc5-c9fa-4108-b56d-0728bc978a22", "is_human": true, "event": "Position", "u": 0.5863, "v": 0.7378, "ts": 1770}, {"user_id": "b3340cc5-c9fa-4108-b56d-0728bc978a22", "is_human": true, "event": "Position", "u": 0.587, "v": 0.7286, "ts": 1770}, {"user_id": "b3340cc5-c9fa-4108-b56d-0728bc978a22", "is_human": true, "event": "Position", "u": 0.5792, "v": 0.7412, "ts": 1770}, {"user_id": "b3340cc5-c9fa-4108-b56d-0728bc978a22", "is_human": true, "event": "Position", "u": 0.6027, "v": 0.734, "ts": 1770}, {"user_id": "b3340cc5-c9fa-4108-b56d-0728bc978a22", "is_human": true, "event": "Position", "u": 0.6291, "v": 0.7209, "ts": 1770}, {"user_id": "b3340cc5-c9fa-4108-b56d-0728bc978a22", "is_human": true, "event": "Position", "u": 0.6247, "v": 0.6922, "ts": 1770}, {"user_id": "b3340cc5-c9fa-4108-b56d-0728bc978a22", "is_human": true, "event": "Position", "u": 0.6152, "v": 0.6717, "ts": 1770}, {"user_id": "b3340cc5-c9fa-4108-b56d-0728bc978a22", "is_human": true, "event": "Position", "u": 0.6025, "v": 0.6489, "ts": 1770}, {"user_id": "b3340cc5-c9fa-4108-b56d-0728bc978a22", "is_human": true, "event": "Position", "u": 0.6077, "v": 0.6232, "ts": 1770}, {"user_id": "b3340cc5-c9fa-4108-b56d-0728bc978a22", "is_human": true, "event": "Position", "u": 0.629, "v": 0.6082, "ts": 1770}, {"user_id": "b3340cc5-c9fa-4108-b56d-0728bc978a22", "is_human": true, "event": "Position", "u": 0.6424, "v": 0.5865, "ts": 1770}, {"user_id": "b3340cc5-c9fa-4108-b56d-0728bc978a22", "is_human": true, "event": "Position", "u": 0.6572, "v": 0.563, "ts": 1770}, {"user_id": "b3340cc5-c9fa-4108-b56d-0728bc978a22", "is_human": true, "event": "Position", "u": 0.6648, "v": 0.535, "ts": 1770}, {"user_id": "b3340cc5-c9fa-4108-b56d-0728bc978a22", "is_human": true, "event": "Position", "u": 0.6697, "v": 0.5171, "ts": 1770}, {"user_id": "b3340cc5-c9fa-4108-b56d-0728bc978a22", "is_human": true, "event": "Position", "u": 0.6755, "v": 0.497, "ts": 1770}, {"user_id": "b3340cc5-c9fa-4108-b56d-0728bc978a22", "is_human": true, "event": "Position", "u": 0.6893, "v": 0.4727, "ts": 1770}, {"user_id": "b3340cc5-c9fa-4108-b56d-0728bc978a22", "is_human": true, "event": "Position", "u": 0.6856, "v": 0.4424, "ts": 1770}, {"user_id": "b3340cc5-c9fa-4108-b56d-0728bc978a22", "is_human": true, "event": "Position", "u": 0.7031, "v": 0.4288, "ts": 1770}, {"user_id": "b3340cc5-c9fa-4108-b56d-0728bc978a22", "is_human": true, "event": "Position", "u": 0.715, "v": 0.4145, "ts": 1770}, {"user_id": "b3340cc5-c9fa-4108-b56d-0728bc978a22", "is_human": true, "event": "Position", "u": 0.7288, "v": 0.4065, "ts": 1770}, {"user_id": "b3340cc5-c9fa-4108-b56d-0728bc978a22", "is_human": true, "event": "Position", "u": 0.7479, "v": 0.4075, "ts": 1770}, {"user_id": "b3340cc5-c9fa-4108-b56d-0728bc978a22", "is_human": true, "event": "Position", "u": 0.7667, "v": 0.4092, "ts": 1770}, {"user_id": "b3340cc5-c9fa-4108-b56d-0728bc978a22", "is_human": true, "event": "Position", "u": 0.779, "v": 0.4169, "ts": 1770}, {"user_id": "b3340cc5-c9fa-4108-b56d-0728bc978a22", "is_human": true, "event": "Position", "u": 0.7829, "v": 0.4281, "ts": 1770}, {"user_id": "b3340cc5-c9fa-4108-b56d-0728bc978a22", "is_human": true, "event": "Position", "u": 0.7771, "v": 0.4196, "ts": 1770}, {"user_id": "b3340cc5-c9fa-4108-b56d-0728bc978a22", "is_human": true, "event": "Position", "u": 0.756, "v": 0.4059, "ts": 1770}, {"user_id": "b3340cc5-c9fa-4108-b56d-0728bc978a22", "is_human": true, "event": "Position", "u": 0.7291, "v": 0.3904, "ts": 1770}, {"user_id": "b3340cc5-c9fa-4108-b56d-0728bc978a22", "is_human": true, "event": "KilledByStorm", "u": 0.7225, "v": 0.3946, "ts": 1770}, {"user_id": "b3340cc5-c9fa-4108-b56d-0728bc978a22", "is_human": true, "event": "Position", "u": 0.7225, "v": 0.3946, "ts": 1770}]}