{"match_id": "a608bc17-d0bf-44a5-83c3-d5ff87341271", "map_id": "AmbroseValley", "date": "2026-02-10", "human_count": 1, "bot_count": 0, "event_counts": {"Position": 58, "Loot": 7, "BotKill": 3, "BotKilled": 1}, "events": [{"user_id": "8afb6ea6-22f2-4af9-8831-1f6ebf723942", "is_human": true, "event": "Position", "u": 0.2952, "v": 0.1187, "ts": 1770}, {"user_id": "8afb6ea6-22f2-4af9-8831-1f6ebf723942", "is_human": true, "event": "Position", "u": 0.3056, "v": 0.1305, "ts": 1770}, {"user_id": "8afb6ea6-22f2-4af9-8831-1f6ebf723942", "is_human": true, "event": "Position", "u": 0.325, "v": 0.1419, "ts": 1770}, {"user_id": "8afb6ea6-22f2-4af9-8831-1f6ebf723942", "is_human": true, "event": "Position", "u": 0.3436, "v": 0.1429, "ts": 1770}, {"user_id": "8afb6ea6-22f2-4af9-8831-1f6ebf723942", "is_human": true, "event": "Position", "u": 0.3585, "v": 0.1342, "ts": 1770}, {"user_id": "8afb6ea6-22f2-4af9-8831-1f6ebf723942", "is_human": true, "event": "Loot", "u": 0.3506, "v": 0.1317, "ts": 1770}, {"user_id": "8afb6ea6-22f2-4af9-8831-1f6ebf723942", "is_human": true, "event": "Position", "u": 0.3532, "v": 0.129, "ts": 1770}, {"user_id": "8afb6ea6-22f2-4af9-8831-1f6ebf723942", "is_human": true, "event": "Loot", "u": 0.3504, "v": 0.1291, "ts": 1770}, {"user_id": "8afb6ea6-22f2-4af9-8831-1f6ebf723942", "is_human": true, "event": "Position", "u": 0.3596, "v": 0.1311, "ts": 1770}, {"user_id": "8afb6ea6-22f2-4af9-8831-1f6ebf723942", "is_human": true, "event": "Position", "u": 0.3634, "v": 0.1319, "ts": 1770}, {"user_id": "8afb6ea6-22f2-4af9-8831-1f6ebf723942", "is_human": true, "event": "Position", "u": 0.37, "v": 0.1296, "ts": 1770}, {"user_id": "8afb6ea6-22f2-4af9-8831-1f6ebf723942", "is_human": true, "event": "Position", "u": 0.3726, "v": 0.1266, "ts": 1770}, {"user_id": "8afb6ea6-22f2-4af9-8831-1f6ebf723942", "is_human": true, "event": "Position", "u": 0.3691, "v": 0.1368, "ts": 1770}, {"user_id": "8afb6ea6-22f2-4af9-8831-1f6ebf723942", "is_human": true, "event": "Position", "u": 0.3977, "v": 0.1451, "ts": 1770}, {"user_id": "8afb6ea6-22f2-4af9-8831-1f6ebf723942", "is_human": true, "event": "Position", "u": 0.4303, "v": 0.1552, "ts": 1770}, {"user_id": "8afb6ea6-22f2-4af9-8831-1f6ebf723942", "is_human": true, "event": "Position", "u": 0.4419, "v": 0.1517, "ts": 1770}, {"user_id": "8afb6ea6-22f2-4af9-8831-1f6ebf723942", "is_human": true, "event": "Position", "u": 0.4526, "v": 0.1575, "ts": 1770}, {"user_id": "8afb6ea6-22f2-4af9-8831-1f6ebf723942", "is_human": true, "event": "Position", "u": 0.4623, "v": 0.1591, "ts": 1770}, {"user_id": "8afb6ea6-22f2-4af9-8831-1f6ebf723942", "is_human": true, "event": "Position", "u": 0.4572, "v": 0.1678, "ts": 1770}, {"user_id": "8afb6ea6-22f2-4af9-8831-1f6ebf723942", "is_human": true, "event": "Position", "u": 0.4613, "v": 0.1667, "ts": 1770}, {"user_id": "8afb6ea6-22f2-4af9-8831-1f6ebf723942", "is_human": true, "event": "Loot", "u": 0.4647, "v": 0.1582, "ts": 1770}, {"user_id": "8afb6ea6-22f2-4af9-8831-1f6ebf723942", "is_human": true, "event": "Position", "u": 0.4664, "v": 0.1598, "ts": 1770}, {"user_id": "8afb6ea6-22f2-4af9-8831-1f6ebf723942", "is_human": true, "event": "Position", "u": 0.4786, "v": 0.1658, "ts": 1770}, {"user_id": "8afb6ea6-22f2-4af9-8831-1f6ebf723942", "is_human": true, "event": "Loot", "u": 0.4786, "v": 0.1658, "ts": 1770}, {"user_id": "8afb6ea6-22f2-4af9-8831-1f6ebf723942", "is_human": true, "event": "Position", "u": 0.4657, "v": 0.1649, "ts": 1770}, {"user_id": "8afb6ea6-22f2-4af9-8831-1f6ebf723942", "is_human": true, "event": "Position", "u": 0.4692, "v": 0.1681, "ts": 1770}, {"user_id": "8afb6ea6-22f2-4af9-8831-1f6ebf723942", "is_human": true, "event": "Position", "u": 0.4808, "v": 0.1673, "ts": 1770}, {"user_id": "8afb6ea6-22f2-4af9-8831-1f6ebf723942", "is_human": true, "event": "Position", "u": 0.4677, "v": 0.1482, "ts": 1770}, {"user_id": "8afb6ea6-22f2-4af9-8831-1f6ebf723942", "is_human": true, "event": "Position", "u": 0.4354, "v": 0.1394, "ts": 1770}, {"user_id": "8afb6ea6-22f2-4af9-8831-1f6ebf723942", "is_human": true, "event": "Position", "u": 0.4153, "v": 0.1637, "ts": 1770}, {"user_id": "8afb6ea6-22f2-4af9-8831-1f6ebf723942", "is_human": true, "event": "Position", "u": 0.4176, "v": 0.1678, "ts": 1770}, {"user_id": "8afb6ea6-22f2-4af9-8831-1f6ebf723942", "is_human": true, "event": "Position", "u": 0.4225, "v": 0.1651, "ts": 1770}, {"user_id": "8afb6ea6-22f2-4af9-8831-1f6ebf723942", "is_human": true, "event": "Position", "u": 0.4305, "v": 0.1824, "ts": 1770}, {"user_id": "8afb6ea6-22f2-4af9-8831-1f6ebf723942", "is_human": true, "event": "Position", "u": 0.4375, "v": 0.2094, "ts": 1770}, {"user_id": "8afb6ea6-22f2-4af9-8831-1f6ebf723942", "is_human": true, "event": "Position", "u": 0.442, "v": 0.216, "ts": 1770}, {"user_id": "8afb6ea6-22f2-4af9-8831-1f6ebf723942", "is_human": true, "event": "BotKill", "u": 0.4368, "v": 0.2177, "ts": 1770}, {"user_id": "8afb6ea6-22f2-4af9-8831-1f6ebf723942", "is_human": true, "event": "Loot", "u": 0.4418, "v": 0.2152, "ts": 1770}, {"user_id": "8afb6ea6-22f2-4af9-8831-1f6ebf723942", "is_human": true, "event": "Position", "u": 0.4515, "v": 0.2119, "ts": 1770}, {"user_id": "8afb6ea6-22f2-4af9-8831-1f6ebf723942", "is_human": true, "event": "Position", "u": 0.4616, "v": 0.2216, "ts": 1770}, {"user_id": "8afb6ea6-22f2-4af9-8831-1f6ebf723942", "is_human": true, "event": "Position", "u": 0.4487, "v": 0.22, "ts": 1770}, {"user_id": "8afb6ea6-22f2-4af9-8831-1f6ebf723942", "is_human": true, "event": "Position", "u": 0.441, "v": 0.2248, "ts": 1770}, {"user_id": "8afb6ea6-22f2-4af9-8831-1f6ebf723942", "is_human": true, "event": "Position", "u": 0.4325, "v": 0.2535, "ts": 1770}, {"user_id": "8afb6ea6-22f2-4af9-8831-1f6ebf723942", "is_human": true, "event": "Position", "u": 0.4237, "v": 0.2761, "ts": 1770}, {"user_id": "8afb6ea6-22f2-4af9-8831-1f6ebf723942", "is_human": true, "event": "Position", "u": 0.4158, "v": 0.3012, "ts": 1770}, {"user_id": "8afb6ea6-22f2-4af9-8831-1f6ebf723942", "is_human": true, "event": "Position", "u": 0.4114, "v": 0.3149, "ts": 1770}, {"user_id": "8afb6ea6-22f2-4af9-8831-1f6ebf723942", "is_human": true, "event": "Position", "u": 0.4159, "v": 0.3274, "ts": 1770}, {"user_id": "8afb6ea6-22f2-4af9-8831-1f6ebf723942", "is_human": true, "event": "Position", "u": 0.41, "v": 0.3469, "ts": 1770}, {"user_id": "8afb6ea6-22f2-4af9-8831-1f6ebf723942", "is_human": true, "event": "Position", "u": 0.4003, "v": 0.3754, "ts": 1770}, {"user_id": "8afb6ea6-22f2-4af9-8831-1f6ebf723942", "is_human": true, "event": "Position", "u": 0.4016, "v": 0.4063, "ts": 1770}, {"user_id": "8afb6ea6-22f2-4af9-8831-1f6ebf723942", "is_human": true, "event": "Position", "u": 0.3992, "v": 0.4328, "ts": 1770}, {"user_id": "8afb6ea6-22f2-4af9-8831-1f6ebf723942", "is_human": true, "event": "BotKill", "u": 0.3924, "v": 0.4343, "ts": 1770}, {"user_id": "8afb6ea6-22f2-4af9-8831-1f6ebf723942", "is_human": true, "event": "Position", "u": 0.3924, "v": 0.4343, "ts": 1770}, {"user_id": "8afb6ea6-22f2-4af9-8831-1f6ebf723942", "is_human": true, "event": "Position", "u": 0.377, "v": 0.4347, "ts": 1770}, {"user_id": "8afb6ea6-22f2-4af9-8831-1f6ebf723942", "is_human": true, "event": "Position", "u": 0.3596, "v": 0.4353, "ts": 1770}, {"user_id": "8afb6ea6-22f2-4af9-8831-1f6ebf723942", "is_human": true, "event": "Loot", "u": 0.3602, "v": 0.4356, "ts": 1770}, {"user_id": "8afb6ea6-22f2-4af9-8831-1f6ebf723942", "is_human": true, "event": "Position", "u": 0.3486, "v": 0.437, "ts": 1770}, {"user_id": "8afb6ea6-22f2-4af9-8831-1f6ebf723942", "is_human": true, "event": "Position", "u": 0.343, "v": 0.4311, "ts": 1770}, {"user_id": "8afb6ea6-22f2-4af9-8831-1f6ebf723942", "is_human": true, "event": "BotKill", "u": 0.3464, "v": 0.4288, "ts": 1770}, {"user_id": "8afb6ea6-22f2-4af9-8831-1f6ebf723942", "is_human": true, "event": "Position", "u": 0.3387, "v": 0.4342, "ts": 1770}, {"user_id": "8afb6ea6-22f2-4af9-8831-1f6ebf723942", "is_human": true, "event": "Loot", "u": 0.3374, "v": 0.4364, "ts": 1770}, {"user_id": "8afb6ea6-22f2-4af9-8831-1f6ebf723942", "is_human": true, "event": "Position", "u": 0.3336, "v": 0.433, "ts": 1770}, {"user_id": "8afb6ea6-22f2-4af9-8831-1f6ebf723942", "is_human": true, "event": "Position", "u": 0.3243, "v": 0.4185, "ts": 1770}, {"user_id": "8afb6ea6-22f2-4af9-8831-1f6ebf723942", "is_human": true, "event": "Position", "u": 0.299, "v": 0.4253, "ts": 1770}, {"user_id": "8afb6ea6-22f2-4af9-8831-1f6ebf723942", "is_human": true, "event": "Position", "u": 0.2696, "v": 0.4354, "ts": 1770}, {"user_id": "8afb6ea6-22f2-4af9-8831-1f6ebf723942", "is_human": true, "event": "Position", "u": 0.2525, "v": 0.4531, "ts": 1770}, {"user_id": "8afb6ea6-22f2-4af9-8831-1f6ebf723942", "is_human": true, "event": "Position", "u": 0.2458, "v": 0.4592, "ts": 1770}, {"user_id": "8afb6ea6-22f2-4af9-8831-1f6ebf723942", "is_human": true, "event": "Position", "u": 0.2608, "v": 0.4716, "ts": 1770}, {"user_id": "8afb6ea6-22f2-4af9-8831-1f6ebf723942", "is_human": true, "event": "Position", "u": 0.2622, "v": 0.4754, "ts": 1770}, {"user_id": "8afb6ea6-22f2-4af9-8831-1f6ebf723942", "is_human": true, "event": "BotKilled", "u": 0.262, "v": 0.4745, "ts": 1770}]}