{"match_id": "dcfed00c-7ca4-4111-950b-415427fea52c", "map_id": "Lockdown", "date": "2026-02-11", "human_count": 1, "bot_count": 0, "event_counts": {"Position": 64, "Loot": 10, "BotKill": 4}, "events": [{"user_id": "83f935e1-3f3e-4046-9309-e2059ea8ffa2", "is_human": true, "event": "Position", "u": 0.3789, "v": 0.5853, "ts": 1770}, {"user_id": "83f935e1-3f3e-4046-9309-e2059ea8ffa2", "is_human": true, "event": "Position", "u": 0.3841, "v": 0.5883, "ts": 1770}, {"user_id": "83f935e1-3f3e-4046-9309-e2059ea8ffa2", "is_human": true, "event": "Position", "u": 0.4094, "v": 0.5891, "ts": 1770}, {"user_id": "83f935e1-3f3e-4046-9309-e2059ea8ffa2", "is_human": true, "event": "Position", "u": 0.4235, "v": 0.5896, "ts": 1770}, {"user_id": "83f935e1-3f3e-4046-9309-e2059ea8ffa2", "is_human": true, "event": "Position", "u": 0.4511, "v": 0.5803, "ts": 1770}, {"user_id": "83f935e1-3f3e-4046-9309-e2059ea8ffa2", "is_human": true, "event": "Position", "u": 0.472, "v": 0.5777, "ts": 1770}, {"user_id": "83f935e1-3f3e-4046-9309-e2059ea8ffa2", "is_human": true, "event": "Position", "u": 0.4768, "v": 0.5729, "ts": 1770}, {"user_id": "83f935e1-3f3e-4046-9309-e2059ea8ffa2", "is_human": true, "event": "Position", "u": 0.4825, "v": 0.5614, "ts": 1770}, {"user_id": "83f935e1-3f3e-4046-9309-e2059ea8ffa2", "is_human": true, "event": "Position", "u": 0.4931, "v": 0.5581, "ts": 1770}, {"user_id": "83f935e1-3f3e-4046-9309-e2059ea8ffa2", "is_human": true, "event": "Loot", "u": 0.5089, "v": 0.5531, "ts": 1770}, {"user_id": "83f935e1-3f3e-4046-9309-e2059ea8ffa2", "is_human": true, "event": "Position", "u": 0.5095, "v": 0.5561, "ts": 1770}, {"user_id": "83f935e1-3f3e-4046-9309-e2059ea8ffa2", "is_human": true, "event": "Position", "u": 0.5038, "v": 0.5695, "ts": 1770}, {"user_id": "83f935e1-3f3e-4046-9309-e2059ea8ffa2", "is_human": true, "event": "Loot", "u": 0.5091, "v": 0.5685, "ts": 1770}, {"user_id": "83f935e1-3f3e-4046-9309-e2059ea8ffa2", "is_human": true, "event": "Position", "u": 0.5133, "v": 0.5679, "ts": 1770}, {"user_id": "83f935e1-3f3e-4046-9309-e2059ea8ffa2", "is_human": true, "event": "Position", "u": 0.5229, "v": 0.5767, "ts": 1770}, {"user_id": "83f935e1-3f3e-4046-9309-e2059ea8ffa2", "is_human": true, "event": "Position", "u": 0.5407, "v": 0.5694, "ts": 1770}, {"user_id": "83f935e1-3f3e-4046-9309-e2059ea8ffa2", "is_human": true, "event": "Position", "u": 0.5652, "v": 0.5603, "ts": 1770}, {"user_id": "83f935e1-3f3e-4046-9309-e2059ea8ffa2", "is_human": true, "event": "Position", "u": 0.5899, "v": 0.5592, "ts": 1770}, {"user_id": "83f935e1-3f3e-4046-9309-e2059ea8ffa2", "is_human": true, "event": "Position", "u": 0.5997, "v": 0.5576, "ts": 1770}, {"user_id": "83f935e1-3f3e-4046-9309-e2059ea8ffa2", "is_human": true, "event": "Position", "u": 0.6137, "v": 0.5545, "ts": 1770}, {"user_id": "83f935e1-3f3e-4046-9309-e2059ea8ffa2", "is_human": true, "event": "Position", "u": 0.6289, "v": 0.5499, "ts": 1770}, {"user_id": "83f935e1-3f3e-4046-9309-e2059ea8ffa2", "is_human": true, "event": "Position", "u": 0.6414, "v": 0.5477, "ts": 1770}, {"user_id": "83f935e1-3f3e-4046-9309-e2059ea8ffa2", "is_human": true, "event": "Position", "u": 0.6427, "v": 0.539, "ts": 1770}, {"user_id": "83f935e1-3f3e-4046-9309-e2059ea8ffa2", "is_human": true, "event": "Position", "u": 0.646, "v": 0.5347, "ts": 1770}, {"user_id": "83f935e1-3f3e-4046-9309-e2059ea8ffa2", "is_human": true, "event": "Position", "u": 0.6425, "v": 0.5317, "ts": 1770}, {"user_id": "83f935e1-3f3e-4046-9309-e2059ea8ffa2", "is_human": true, "event": "Position", "u": 0.6382, "v": 0.5362, "ts": 1770}, {"user_id": "83f935e1-3f3e-4046-9309-e2059ea8ffa2", "is_human": true, "event": "Position", "u": 0.6418, "v": 0.5353, "ts": 1770}, {"user_id": "83f935e1-3f3e-4046-9309-e2059ea8ffa2", "is_human": true, "event": "Position", "u": 0.6362, "v": 0.5294, "ts": 1770}, {"user_id": "83f935e1-3f3e-4046-9309-e2059ea8ffa2", "is_human": true, "event": "Position", "u": 0.6319, "v": 0.5257, "ts": 1770}, {"user_id": "83f935e1-3f3e-4046-9309-e2059ea8ffa2", "is_human": true, "event": "Position", "u": 0.6369, "v": 0.5308, "ts": 1770}, {"user_id": "83f935e1-3f3e-4046-9309-e2059ea8ffa2", "is_human": true, "event": "Position", "u": 0.6326, "v": 0.5262, "ts": 1770}, {"user_id": "83f935e1-3f3e-4046-9309-e2059ea8ffa2", "is_human": true, "event": "Position", "u": 0.6398, "v": 0.5356, "ts": 1770}, {"user_id": "83f935e1-3f3e-4046-9309-e2059ea8ffa2", "is_human": true, "event": "Position", "u": 0.6413, "v": 0.5348, "ts": 1770}, {"user_id": "83f935e1-3f3e-4046-9309-e2059ea8ffa2", "is_human": true, "event": "Position", "u": 0.644, "v": 0.5382, "ts": 1770}, {"user_id": "83f935e1-3f3e-4046-9309-e2059ea8ffa2", "is_human": true, "event": "Position", "u": 0.6408, "v": 0.5311, "ts": 1770}, {"user_id": "83f935e1-3f3e-4046-9309-e2059ea8ffa2", "is_human": true, "event": "Position", "u": 0.6461, "v": 0.522, "ts": 1770}, {"user_id": "83f935e1-3f3e-4046-9309-e2059ea8ffa2", "is_human": true, "event": "Position", "u": 0.6633, "v": 0.5336, "ts": 1770}, {"user_id": "83f935e1-3f3e-4046-9309-e2059ea8ffa2", "is_human": true, "event": "Position", "u": 0.6446, "v": 0.5554, "ts": 1770}, {"user_id": "83f935e1-3f3e-4046-9309-e2059ea8ffa2", "is_human": true, "event": "Loot", "u": 0.6405, "v": 0.5633, "ts": 1770}, {"user_id": "83f935e1-3f3e-4046-9309-e2059ea8ffa2", "is_human": true, "event": "Position", "u": 0.6487, "v": 0.5716, "ts": 1770}, {"user_id": "83f935e1-3f3e-4046-9309-e2059ea8ffa2", "is_human": true, "event": "Position", "u": 0.6631, "v": 0.5854, "ts": 1770}, {"user_id": "83f935e1-3f3e-4046-9309-e2059ea8ffa2", "is_human": true, "event": "Position", "u": 0.6665, "v": 0.5829, "ts": 1770}, {"user_id": "83f935e1-3f3e-4046-9309-e2059ea8ffa2", "is_human": true, "event": "BotKill", "u": 0.6705, "v": 0.5873, "ts": 1770}, {"user_id": "83f935e1-3f3e-4046-9309-e2059ea8ffa2", "is_human": true, "event": "Position", "u": 0.6687, "v": 0.588, "ts": 1770}, {"user_id": "83f935e1-3f3e-4046-9309-e2059ea8ffa2", "is_human": true, "event": "Position", "u": 0.6749, "v": 0.5943, "ts": 1770}, {"user_id": "83f935e1-3f3e-4046-9309-e2059ea8ffa2", "is_human": true, "event": "Position", "u": 0.6775, "v": 0.595, "ts": 1770}, {"user_id": "83f935e1-3f3e-4046-9309-e2059ea8ffa2", "is_human": true, "event": "Position", "u": 0.6886, "v": 0.6045, "ts": 1770}, {"user_id": "83f935e1-3f3e-4046-9309-e2059ea8ffa2", "is_human": true, "event": "BotKill", "u": 0.7016, "v": 0.609, "ts": 1770}, {"user_id": "83f935e1-3f3e-4046-9309-e2059ea8ffa2", "is_human": true, "event": "BotKill", "u": 0.7017, "v": 0.6091, "ts": 1770}, {"user_id": "83f935e1-3f3e-4046-9309-e2059ea8ffa2", "is_human": true, "event": "BotKill", "u": 0.7017, "v": 0.6091, "ts": 1770}, {"user_id": "83f935e1-3f3e-4046-9309-e2059ea8ffa2", "is_human": true, "event": "Position", "u": 0.702, "v": 0.6093, "ts": 1770}, {"user_id": "83f935e1-3f3e-4046-9309-e2059ea8ffa2", "is_human": true, "event": "Position", "u": 0.7155, "v": 0.5986, "ts": 1770}, {"user_id": "83f935e1-3f3e-4046-9309-e2059ea8ffa2", "is_human": true, "event": "Position", "u": 0.7157, "v": 0.6018, "ts": 1770}, {"user_id": "83f935e1-3f3e-4046-9309-e2059ea8ffa2", "is_human": true, "event": "Loot", "u": 0.704, "v": 0.5903, "ts": 1770}, {"user_id": "83f935e1-3f3e-4046-9309-e2059ea8ffa2", "is_human": true, "event": "Position", "u": 0.7064, "v": 0.5823, "ts": 1770}, {"user_id": "83f935e1-3f3e-4046-9309-e2059ea8ffa2", "is_human": true, "event": "Loot", "u": 0.7098, "v": 0.5751, "ts": 1770}, {"user_id": "83f935e1-3f3e-4046-9309-e2059ea8ffa2", "is_human": true, "event": "Position", "u": 0.6984, "v": 0.5861, "ts": 1770}, {"user_id": "83f935e1-3f3e-4046-9309-e2059ea8ffa2", "is_human": true, "event": "Loot", "u": 0.6791, "v": 0.5792, "ts": 1770}, {"user_id": "83f935e1-3f3e-4046-9309-e2059ea8ffa2", "is_human": true, "event": "Position", "u": 0.6791, "v": 0.5792, "ts": 1770}, {"user_id": "83f935e1-3f3e-4046-9309-e2059ea8ffa2", "is_human": true, "event": "Loot", "u": 0.6791, "v": 0.5792, "ts": 1770}, {"user_id": "83f935e1-3f3e-4046-9309-e2059ea8ffa2", "is_human": true, "event": "Position", "u": 0.685, "v": 0.5926, "ts": 1770}, {"user_id": "83f935e1-3f3e-4046-9309-e2059ea8ffa2", "is_human": true, "event": "Position", "u": 0.7047, "v": 0.5924, "ts": 1770}, {"user_id": "83f935e1-3f3e-4046-9309-e2059ea8ffa2", "is_human": true, "event": "Position", "u": 0.6994, "v": 0.5962, "ts": 1770}, {"user_id": "83f935e1-3f3e-4046-9309-e2059ea8ffa2", "is_human": true, "event": "Position", "u": 0.7279, "v": 0.6008, "ts": 1770}, {"user_id": "83f935e1-3f3e-4046-9309-e2059ea8ffa2", "is_human": true, "event": "Position", "u": 0.7082, "v": 0.5994, "ts": 1770}, {"user_id": "83f935e1-3f3e-4046-9309-e2059ea8ffa2", "is_human": true, "event": "Loot", "u": 0.7082, "v": 0.5994, "ts": 1770}, {"user_id": "83f935e1-3f3e-4046-9309-e2059ea8ffa2", "is_human": true, "event": "Loot", "u": 0.7038, "v": 0.5905, "ts": 1770}, {"user_id": "83f935e1-3f3e-4046-9309-e2059ea8ffa2", "is_human": true, "event": "Position", "u": 0.7037, "v": 0.5901, "ts": 1770}, {"user_id": "83f935e1-3f3e-4046-9309-e2059ea8ffa2", "is_human": true, "event": "Position", "u": 0.7142, "v": 0.573, "ts": 1770}, {"user_id": "83f935e1-3f3e-4046-9309-e2059ea8ffa2", "is_human": true, "event": "Position", "u": 0.7286, "v": 0.5749, "ts": 1770}, {"user_id": "83f935e1-3f3e-4046-9309-e2059ea8ffa2", "is_human": true, "event": "Loot", "u": 0.7307, "v": 0.5751, "ts": 1770}, {"user_id": "83f935e1-3f3e-4046-9309-e2059ea8ffa2", "is_human": true, "event": "Position", "u": 0.7308, "v": 0.5719, "ts": 1770}, {"user_id": "83f935e1-3f3e-4046-9309-e2059ea8ffa2", "is_human": true, "event": "Position", "u": 0.7516, "v": 0.5745, "ts": 1770}, {"user_id": "83f935e1-3f3e-4046-9309-e2059ea8ffa2", "is_human": true, "event": "Position", "u": 0.7575, "v": 0.5832, "ts": 1770}, {"user_id": "83f935e1-3f3e-4046-9309-e2059ea8ffa2", "is_human": true, "event": "Position", "u": 0.7876, "v": 0.5945, "ts": 1770}, {"user_id": "83f935e1-3f3e-4046-9309-e2059ea8ffa2", "is_human": true, "event": "Position", "u": 0.7968, "v": 0.5939, "ts": 1770}, {"user_id": "83f935e1-3f3e-4046-9309-e2059ea8ffa2", "is_human": true, "event": "Position", "u": 0.8124, "v": 0.603, "ts": 1770}, {"user_id": "83f935e1-3f3e-4046-9309-e2059ea8ffa2", "is_human": true, "event": "Position", "u": 0.8116, "v": 0.6081, "ts": 1770}]}