{"match_id": "fa40a54c-10f9-483c-b547-e0b4d0d407de", "map_id": "AmbroseValley", "date": "2026-02-10", "human_count": 1, "bot_count": 0, "event_counts": {"Position": 17, "BotKilled": 1}, "events": [{"user_id": "09009296-eb20-4df3-9350-6de46132ff74", "is_human": true, "event": "Position", "u": 0.6719, "v": 0.7629, "ts": 1770}, {"user_id": "09009296-eb20-4df3-9350-6de46132ff74", "is_human": true, "event": "Position", "u": 0.6547, "v": 0.7499, "ts": 1770}, {"user_id": "09009296-eb20-4df3-9350-6de46132ff74", "is_human": true, "event": "Position", "u": 0.6207, "v": 0.7541, "ts": 1770}, {"user_id": "09009296-eb20-4df3-9350-6de46132ff74", "is_human": true, "event": "Position", "u": 0.5931, "v": 0.735, "ts": 1770}, {"user_id": "09009296-eb20-4df3-9350-6de46132ff74", "is_human": true, "event": "Position", "u": 0.5694, "v": 0.7113, "ts": 1770}, {"user_id": "09009296-eb20-4df3-9350-6de46132ff74", "is_human": true, "event": "Position", "u": 0.5587, "v": 0.6948, "ts": 1770}, {"user_id": "09009296-eb20-4df3-9350-6de46132ff74", "is_human": true, "event": "Position", "u": 0.5553, "v": 0.6864, "ts": 1770}, {"user_id": "09009296-eb20-4df3-9350-6de46132ff74", "is_human": true, "event": "Position", "u": 0.5405, "v": 0.6722, "ts": 1770}, {"user_id": "09009296-eb20-4df3-9350-6de46132ff74", "is_human": true, "event": "Position", "u": 0.5134, "v": 0.6526, "ts": 1770}, {"user_id": "09009296-eb20-4df3-9350-6de46132ff74", "is_human": true, "event": "Position", "u": 0.4921, "v": 0.6286, "ts": 1770}, {"user_id": "09009296-eb20-4df3-9350-6de46132ff74", "is_human": true, "event": "Position", "u": 0.4792, "v": 0.6071, "ts": 1770}, {"user_id": "09009296-eb20-4df3-9350-6de46132ff74", "is_human": true, "event": "Position", "u": 0.4573, "v": 0.5802, "ts": 1770}, {"user_id": "09009296-eb20-4df3-9350-6de46132ff74", "is_human": true, "event": "Position", "u": 0.4398, "v": 0.5659, "ts": 1770}, {"user_id": "09009296-eb20-4df3-9350-6de46132ff74", "is_human": true, "event": "Position", "u": 0.4178, "v": 0.5392, "ts": 1770}, {"user_id": "09009296-eb20-4df3-9350-6de46132ff74", "is_human": true, "event": "Position", "u": 0.4132, "v": 0.5295, "ts": 1770}, {"user_id": "09009296-eb20-4df3-9350-6de46132ff74", "is_human": true, "event": "Position", "u": 0.4179, "v": 0.5277, "ts": 1770}, {"user_id": "09009296-eb20-4df3-9350-6de46132ff74", "is_human": true, "event": "Position", "u": 0.4166, "v": 0.5298, "ts": 1770}, {"user_id": "09009296-eb20-4df3-9350-6de46132ff74", "is_human": true, "event": "BotKilled", "u": 0.4166, "v": 0.5298, "ts": 1770}]}